Workbook

Sheet Executive_KPI_Dashboard
A1: RETAIL SALES & CUSTOMER ANALYTICS — EXECUTIVE KPI DASHBOARD
A3: Dataset: 530 Transactions | 280 Orders | 110 Customers | 5 Geographic Regions | Generated: 2026-10-30
B5: TOTAL NET REVENUE | D5: TOTAL GROSS PROFIT | F5: OVERALL PROFIT MARGIN | H5: TOTAL COMPLETED ORDERS | J5: AVERAGE ORDER VALUE (AOV)
B6: =SUM(Sales_Transactions!M2:M531) | D6: =SUM(Sales_Transactions!O2:O531) | F6: =D6/B6 | H6: =COUNTIF(Sales_Transactions!Q2:Q531, "<>Cancelled") | J6: =B6/H6
B9: Merchandise Category Performance Breakdown
B10: Category | C10: Orders Count | D10: Units Sold | E10: Net Revenue (INR) | F10: Total Profit (INR) | G10: Profit Margin
B11: Electronics | C11: =COUNTIFS(Sales_Transactions!G:G, "Electronics", Sales_Transactions!Q:Q, "<>Cancelled") | D11: =SUMIFS(Sales_Transactions!H:H, Sales_Transactions!G:G, "Electronics", Sales_Transactions!Q:Q, "<>Cancelled") | E11: =SUMIFS(Sales_Transactions!M:M, Sales_Transactions!G:G, "Electronics", Sales_Transactions!Q:Q, "<>Cancelled") | F11: =SUMIFS(Sales_Transactions!O:O, Sales_Transactions!G:G, "Electronics", Sales_Transactions!Q:Q, "<>Cancelled") | G11: =F11/E11
B12: Fashion | C12: =COUNTIFS(Sales_Transactions!G:G, "Fashion", Sales_Transactions!Q:Q, "<>Cancelled") | D12: =SUMIFS(Sales_Transactions!H:H, Sales_Transactions!G:G, "Fashion", Sales_Transactions!Q:Q, "<>Cancelled") | E12: =SUMIFS(Sales_Transactions!M:M, Sales_Transactions!G:G, "Fashion", Sales_Transactions!Q:Q, "<>Cancelled") | F12: =SUMIFS(Sales_Transactions!O:O, Sales_Transactions!G:G, "Fashion", Sales_Transactions!Q:Q, "<>Cancelled") | G12: =F12/E12
B13: Groceries | C13: =COUNTIFS(Sales_Transactions!G:G, "Groceries", Sales_Transactions!Q:Q, "<>Cancelled") | D13: =SUMIFS(Sales_Transactions!H:H, Sales_Transactions!G:G, "Groceries", Sales_Transactions!Q:Q, "<>Cancelled") | E13: =SUMIFS(Sales_Transactions!M:M, Sales_Transactions!G:G, "Groceries", Sales_Transactions!Q:Q, "<>Cancelled") | F13: =SUMIFS(Sales_Transactions!O:O, Sales_Transactions!G:G, "Groceries", Sales_Transactions!Q:Q, "<>Cancelled") | G13: =F13/E13
B14: Home & Living | C14: =COUNTIFS(Sales_Transactions!G:G, "Home & Living", Sales_Transactions!Q:Q, "<>Cancelled") | D14: =SUMIFS(Sales_Transactions!H:H, Sales_Transactions!G:G, "Home & Living", Sales_Transactions!Q:Q, "<>Cancelled") | E14: =SUMIFS(Sales_Transactions!M:M, Sales_Transactions!G:G, "Home & Living", Sales_Transactions!Q:Q, "<>Cancelled") | F14: =SUMIFS(Sales_Transactions!O:O, Sales_Transactions!G:G, "Home & Living", Sales_Transactions!Q:Q, "<>Cancelled") | G14: =F14/E14
B15: Sports | C15: =COUNTIFS(Sales_Transactions!G:G, "Sports", Sales_Transactions!Q:Q, "<>Cancelled") | D15: =SUMIFS(Sales_Transactions!H:H, Sales_Transactions!G:G, "Sports", Sales_Transactions!Q:Q, "<>Cancelled") | E15: =SUMIFS(Sales_Transactions!M:M, Sales_Transactions!G:G, "Sports", Sales_Transactions!Q:Q, "<>Cancelled") | F15: =SUMIFS(Sales_Transactions!O:O, Sales_Transactions!G:G, "Sports", Sales_Transactions!Q:Q, "<>Cancelled") | G15: =F15/E15
B16: Grand Total | C16: =SUM(C11:C15) | D16: =SUM(D11:D15) | E16: =SUM(E11:E15) | F16: =SUM(F11:F15) | G16: =F16/E16
B18: Geographic Regional Distribution
B19: Region | C19: Order Count | D19: Net Revenue (INR) | E19: Profit (INR) | F19: AOV (INR)
B20: East | C20: =COUNTIFS(Sales_Transactions!D:D, "East", Sales_Transactions!Q:Q, "<>Cancelled") | D20: =SUMIFS(Sales_Transactions!M:M, Sales_Transactions!D:D, "East", Sales_Transactions!Q:Q, "<>Cancelled") | E20: =SUMIFS(Sales_Transactions!O:O, Sales_Transactions!D:D, "East", Sales_Transactions!Q:Q, "<>Cancelled") | F20: =D20/C20
B21: Central | C21: =COUNTIFS(Sales_Transactions!D:D, "Central", Sales_Transactions!Q:Q, "<>Cancelled") | D21: =SUMIFS(Sales_Transactions!M:M, Sales_Transactions!D:D, "Central", Sales_Transactions!Q:Q, "<>Cancelled") | E21: =SUMIFS(Sales_Transactions!O:O, Sales_Transactions!D:D, "Central", Sales_Transactions!Q:Q, "<>Cancelled") | F21: =D21/C21
B22: South | C22: =COUNTIFS(Sales_Transactions!D:D, "South", Sales_Transactions!Q:Q, "<>Cancelled") | D22: =SUMIFS(Sales_Transactions!M:M, Sales_Transactions!D:D, "South", Sales_Transactions!Q:Q, "<>Cancelled") | E22: =SUMIFS(Sales_Transactions!O:O, Sales_Transactions!D:D, "South", Sales_Transactions!Q:Q, "<>Cancelled") | F22: =D22/C22
B23: North | C23: =COUNTIFS(Sales_Transactions!D:D, "North", Sales_Transactions!Q:Q, "<>Cancelled") | D23: =SUMIFS(Sales_Transactions!M:M, Sales_Transactions!D:D, "North", Sales_Transactions!Q:Q, "<>Cancelled") | E23: =SUMIFS(Sales_Transactions!O:O, Sales_Transactions!D:D, "North", Sales_Transactions!Q:Q, "<>Cancelled") | F23: =D23/C23
B24: West | C24: =COUNTIFS(Sales_Transactions!D:D, "West", Sales_Transactions!Q:Q, "<>Cancelled") | D24: =SUMIFS(Sales_Transactions!M:M, Sales_Transactions!D:D, "West", Sales_Transactions!Q:Q, "<>Cancelled") | E24: =SUMIFS(Sales_Transactions!O:O, Sales_Transactions!D:D, "West", Sales_Transactions!Q:Q, "<>Cancelled") | F24: =D24/C24
B25: Grand Total | C25: =SUM(C20:C24) | D25: =SUM(D20:D24) | E25: =SUM(E20:E24) | F25: =D25/C25

Sheet Sales_Transactions
A1: Order_ID | B1: Order_Date | C1: Customer_Name | D1: Region | E1: City | F1: Product_Name | G1: Category | H1: Quantity | I1: Unit_Price_INR | J1: Discount_Pct | K1: Gross_Amount_INR | L1: Discount_Amount_INR | M1: Net_Amount_INR | N1: Total_Cost_INR | O1: Profit_INR | P1: Profit_Margin_Pct | Q1: Order_Status
A2: 1 | B2: 2025-06-14 | C2: Arjun Choudhury | D2: East | E2: Patna | F2: Women Floral Embroidered Kurti | G2: Fashion | H2: 1 | I2: 1899 | J2: 0.12 | K2: =H2*I2 | L2: =K2*J2 | M2: =K2-L2 | N2: 800 | O2: =M2-N2 | P2: =IFERROR(O2/M2, 0) | Q2: Delivered
A3: 1 | B3: 2025-06-14 | C3: Arjun Choudhury | D3: East | E3: Patna | F3: Unisex Classic Denim Jeans | G3: Fashion | H3: 1 | I3: 2499 | J3: 0 | K3: =H3*I3 | L3: =K3*J3 | M3: =K3-L3 | N3: 1100 | O3: =M3-N3 | P3: =IFERROR(O3/M3, 0) | Q3: Delivered
A4: 2 | B4: 2025-05-16 | C4: Suresh Saxena | D4: Central | E4: Bhopal | F4: Men Slim-Fit Cotton Casual Shirt | G4: Fashion | H4: 1 | I4: 1499 | J4: 0.1 | K4: =H4*I4 | L4: =K4*J4 | M4: =K4-L4 | N4: 650 | O4: =M4-N4 | P4: =IFERROR(O4/M4, 0) | Q4: Processing
A5: 3 | B5: 2025-08-05 | C5: Shreya Kapoor | D5: East | E5: Bhubaneswar | F5: Men Slim-Fit Cotton Casual Shirt | G5: Fashion | H5: 2 | I5: 1499 | J5: 0.1 | K5: =H5*I5 | L5: =K5*J5 | M5: =K5-L5 | N5: 1300 | O5: =M5-N5 | P5: =IFERROR(O5/M5, 0) | Q5: Delivered
A6: 4 | B6: 2024-11-11 | C6: Nandini Patel | D6: West | E6: Nagpur | F6: Premium California Almonds 500g | G6: Groceries | H6: 1 | I6: 599 | J6: 0.05 | K6: =H6*I6 | L6: =K6*J6 | M6: =K6-L6 | N6: 380 | O6: =M6-N6 | P6: =IFERROR(O6/M6, 0) | Q6: Cancelled
A7: 4 | B7: 2024-11-11 | C7: Nandini Patel | D7: West | E7: Nagpur | F7: Stainless Steel Electric Kettle 1.8L | G7: Home & Living | H7: 1 | I7: 1299 | J7: 0.1 | K7: =H7*I7 | L7: =K7*J7 | M7: =K7-L7 | N7: 720 | O7: =M7-N7 | P7: =IFERROR(O7/M7, 0) | Q7: Cancelled
A8: 4 | B8: 2024-11-11 | C8: Nandini Patel | D8: West | E8: Nagpur | F8: Multipurpose Desk Organizer Set | G8: Home & Living | H8: 3 | I8: 699 | J8: 0.2 | K8: =H8*I8 | L8: =K8*J8 | M8: =K8-L8 | N8: 870 | O8: =M8-N8 | P8: =IFERROR(O8/M8, 0) | Q8: Cancelled
A9: 5 | B9: 2025-08-03 | C9: Kavita Nair | D9: West | E9: Pune | F9: Pure Raw Honey 500g | G9: Groceries | H9: 1 | I9: 399 | J9: 0.05 | K9: =H9*I9 | L9: =K9*J9 | M9: =K9-L9 | N9: 210 | O9: =M9-N9 | P9: =IFERROR(O9/M9, 0) | Q9: Processing
A10: 5 | B10: 2025-08-03 | C10: Kavita Nair | D10: West | E10: Pune | F10: Women Floral Embroidered Kurti | G10: Fashion | H10: 1 | I10: 1899 | J10: 0 | K10: =H10*I10 | L10: =K10*J10 | M10: =K10-L10 | N10: 800 | O10: =M10-N10 | P10: =IFERROR(O10/M10, 0) | Q10: Processing
A11: 6 | B11: 2025-04-22 | C11: Aarav Verma | D11: South | E11: Chennai | F11: Stainless Steel Electric Kettle 1.8L | G11: Home & Living | H11: 1 | I11: 1299 | J11: 0.1 | K11: =H11*I11 | L11: =K11*J11 | M11: =K11-L11 | N11: 720 | O11: =M11-N11 | P11: =IFERROR(O11/M11, 0) | Q11: Processing
A12: 6 | B12: 2025-04-22 | C12: Aarav Verma | D12: South | E12: Chennai | F12: Skipping Rope with Digital Counter | G12: Sports | H12: 3 | I12: 499 | J12: 0.12 | K12: =H12*I12 | L12: =K12*J12 | M12: =K12-L12 | N12: 630 | O12: =M12-N12 | P12: =IFERROR(O12/M12, 0) | Q12: Processing
A13: 7 | B13: 2024-11-14 | C13: Harsh Singh | D13: West | E13: Ahmedabad | F13: Adjustable Dumbbell Set 20kg | G13: Sports | H13: 1 | I13: 4299 | J13: 0.1 | K13: =H13*I13 | L13: =K13*J13 | M13: =K13-L13 | N13: 2600 | O13: =M13-N13 | P13: =IFERROR(O13/M13, 0) | Q13: Delivered
... A531: 280 | B531: 2025-02-16 | C531: Ishaan Sharma | D531: North | E531: Gurgaon | F531: Orthopedic Memory Foam Pillow | G531: Home & Living | H531: 2 | I531: 1799 | J531: 0 | K531: =H531*I531 | L531: =K531*J531 | M531: =K531-L531 | N531: 1900 | O531: =M531-N531 | P531: =IFERROR(O531/M531, 0) | Q531: Cancelled

Sheet Advanced_Formulas_Lab
A1: EXCEL PRACTICAL: ADVANCED LOGICAL & AGGREGATE FORMULAS
A4: Formula Type | B4: Function Syntax | C4: Target Data Column | D4: Business Purpose & Logic | E4: Live Formula Output
A5: IF | B5: =IF(Sales_Transactions!M2>=5000, "High Value", "Standard") | C5: Net_Amount_INR (Col M) | D5: Binary threshold check: tags transaction as 'High Value' if amount >= ₹5,000. | E5: =IF(Sales_Transactions!M2>=5000, "High Value", "Standard")
A6: Nested IF | B6: =IF(Sales_Transactions!M2>=25000, "Tier 1", IF(Sales_Transactions!M2>=10000, "Tier 2", IF(Sales_Transactions!M2>=3000, "Tier 3", "Tier 4"))) | C6: Net_Amount_INR (Col M) | D6: Hierarchical spend tiering: Tier 1 (>=₹25K), Tier 2 (>=₹10K), Tier 3 (>=₹3K), Tier 4 (<₹3K). | E6: =IF(Sales_Transactions!M2>=25000, "Tier 1", IF(Sales_Transactions!M2>=10000, "Tier 2", IF(Sales_Transactions!M2>=3000, "Tier 3", "Tier 4")))
A7: AND | B7: =IF(AND(Sales_Transactions!M2>=5000, Sales_Transactions!Q2="Delivered"), "Qualifies For Loyalty Bonus", "No Bonus") | C7: Net Amount & Order Status | D7: Conjunctive test: requires order to be high-value (>=₹5,000) AND successfully Delivered. | E7: =IF(AND(Sales_Transactions!M2>=5000, Sales_Transactions!Q2="Delivered"), "Qualifies For Loyalty Bonus", "No Bonus")
A8: OR | B8: =IF(OR(Sales_Transactions!D2="North", Sales_Transactions!D2="South"), "Priority Delivery Zone", "Standard Zone") | C8: Region (Col D) | D8: Disjunctive test: tags transaction if order destination is either North OR South region. | E8: =IF(OR(Sales_Transactions!D2="North", Sales_Transactions!D2="South"), "Priority Delivery Zone", "Standard Zone")
A9: NOT | B9: =IF(NOT(Sales_Transactions!Q2="Cancelled"), "Valid Sale", "Excluded") | C9: Order_Status (Col Q) | D9: Logical negation: isolates active/valid revenue transactions by excluding Cancelled orders. | E9: =IF(NOT(Sales_Transactions!Q2="Cancelled"), "Valid Sale", "Excluded")
A10: IFERROR | B10: =IFERROR(Sales_Transactions!O2/Sales_Transactions!M2, 0) | C10: Profit / Net Amount | D10: Fault-tolerance error handler: prevents #DIV/0! or #VALUE! runtime crashes on division. | E10: =IFERROR(Sales_Transactions!O2/Sales_Transactions!M2, 0)
A11: SUMIF | B11: =SUMIF(Sales_Transactions!G:G, "Electronics", Sales_Transactions!M:M) | C11: Category (G) & Net Amount (M) | D11: Conditional summation: totals realized net revenue specifically for the Electronics department. | E11: =SUMIF(Sales_Transactions!G:G, "Electronics", Sales_Transactions!M:M)
A12: AVERAGEIF | B12: =AVERAGEIF(Sales_Transactions!G:G, "Fashion", Sales_Transactions!M:M) | C12: Category (G) & Net Amount (M) | D12: Conditional average: computes arithmetic mean ticket price for the Fashion department. | E12: =AVERAGEIF(Sales_Transactions!G:G, "Fashion", Sales_Transactions!M:M)
A13: COUNTIF | B13: =COUNTIF(Sales_Transactions!Q:Q, "Delivered") | C13: Order_Status (Col Q) | D13: Conditional frequency: counts the exact count of fully fulfilled 'Delivered' orders. | E13: =COUNTIF(Sales_Transactions!Q:Q, "Delivered")
A16: Live Formula Evaluation Grid (Applied Row-by-Row on First 15 Orders)
A17: Row | B17: Order ID | C17: Customer | D17: Net Amount | E17: Status | F17: IF Test | G17: Nested IF Tier | H17: AND Bonus | I17: OR Zone | J17: NOT Audit | K17: Margin (IFERROR)
A18: 1 | B18: =Sales_Transactions!A2 | C18: =Sales_Transactions!C2 | D18: =Sales_Transactions!M2 | E18: =Sales_Transactions!Q2 | F18: =IF(Sales_Transactions!M2>=5000, "High Value", "Standard") | G18: =IF(Sales_Transactions!M2>=25000, "Tier 1", IF(Sales_Transactions!M2>=10000, "Tier 2", IF(Sales_Transactions!M2>=3000, "Tier 3", "Tier 4"))) | H18: =IF(AND(Sales_Transactions!M2>=5000, Sales_Transactions!Q2="Delivered"), "Bonus", "No") | I18: =IF(OR(Sales_Transactions!D2="North", Sales_Transactions!D2="South"), "Priority", "Standard") | J18: =IF(NOT(Sales_Transactions!Q2="Cancelled"), "Valid", "Excluded") | K18: =IFERROR(Sales_Transactions!O2/Sales_Transactions!M2, 0)
A19: 2 | B19: =Sales_Transactions!A3 | C19: =Sales_Transactions!C3 | D19: =Sales_Transactions!M3 | E19: =Sales_Transactions!Q3 | F19: =IF(Sales_Transactions!M3>=5000, "High Value", "Standard") | G19: =IF(Sales_Transactions!M3>=25000, "Tier 1", IF(Sales_Transactions!M3>=10000, "Tier 2", IF(Sales_Transactions!M3>=3000, "Tier 3", "Tier 4"))) | H19: =IF(AND(Sales_Transactions!M3>=5000, Sales_Transactions!Q3="Delivered"), "Bonus", "No") | I19: =IF(OR(Sales_Transactions!D3="North", Sales_Transactions!D3="South"), "Priority", "Standard") | J19: =IF(NOT(Sales_Transactions!Q3="Cancelled"), "Valid", "Excluded") | K19: =IFERROR(Sales_Transactions!O3/Sales_Transactions!M3, 0)
A20: 3 | B20: =Sales_Transactions!A4 | C20: =Sales_Transactions!C4 | D20: =Sales_Transactions!M4 | E20: =Sales_Transactions!Q4 | F20: =IF(Sales_Transactions!M4>=5000, "High Value", "Standard") | G20: =IF(Sales_Transactions!M4>=25000, "Tier 1", IF(Sales_Transactions!M4>=10000, "Tier 2", IF(Sales_Transactions!M4>=3000, "Tier 3", "Tier 4"))) | H20: =IF(AND(Sales_Transactions!M4>=5000, Sales_Transactions!Q4="Delivered"), "Bonus", "No") | I20: =IF(OR(Sales_Transactions!D4="North", Sales_Transactions!D4="South"), "Priority", "Standard") | J20: =IF(NOT(Sales_Transactions!Q4="Cancelled"), "Valid", "Excluded") | K20: =IFERROR(Sales_Transactions!O4/Sales_Transactions!M4, 0)
A21: 4 | B21: =Sales_Transactions!A5 | C21: =Sales_Transactions!C5 | D21: =Sales_Transactions!M5 | E21: =Sales_Transactions!Q5 | F21: =IF(Sales_Transactions!M5>=5000, "High Value", "Standard") | G21: =IF(Sales_Transactions!M5>=25000, "Tier 1", IF(Sales_Transactions!M5>=10000, "Tier 2", IF(Sales_Transactions!M5>=3000, "Tier 3", "Tier 4"))) | H21: =IF(AND(Sales_Transactions!M5>=5000, Sales_Transactions!Q5="Delivered"), "Bonus", "No") | I21: =IF(OR(Sales_Transactions!D5="North", Sales_Transactions!D5="South"), "Priority", "Standard") | J21: =IF(NOT(Sales_Transactions!Q5="Cancelled"), "Valid", "Excluded") | K21: =IFERROR(Sales_Transactions!O5/Sales_Transactions!M5, 0)
A22: 5 | B22: =Sales_Transactions!A6 | C22: =Sales_Transactions!C6 | D22: =Sales_Transactions!M6 | E22: =Sales_Transactions!Q6 | F22: =IF(Sales_Transactions!M6>=5000, "High Value", "Standard") | G22: =IF(Sales_Transactions!M6>=25000, "Tier 1", IF(Sales_Transactions!M6>=10000, "Tier 2", IF(Sales_Transactions!M6>=3000, "Tier 3", "Tier 4"))) | H22: =IF(AND(Sales_Transactions!M6>=5000, Sales_Transactions!Q6="Delivered"), "Bonus", "No") | I22: =IF(OR(Sales_Transactions!D6="North", Sales_Transactions!D6="South"), "Priority", "Standard") | J22: =IF(NOT(Sales_Transactions!Q6="Cancelled"), "Valid", "Excluded") | K22: =IFERROR(Sales_Transactions!O6/Sales_Transactions!M6, 0)
A23: 6 | B23: =Sales_Transactions!A7 | C23: =Sales_Transactions!C7 | D23: =Sales_Transactions!M7 | E23: =Sales_Transactions!Q7 | F23: =IF(Sales_Transactions!M7>=5000, "High Value", "Standard") | G23: =IF(Sales_Transactions!M7>=25000, "Tier 1", IF(Sales_Transactions!M7>=10000, "Tier 2", IF(Sales_Transactions!M7>=3000, "Tier 3", "Tier 4"))) | H23: =IF(AND(Sales_Transactions!M7>=5000, Sales_Transactions!Q7="Delivered"), "Bonus", "No") | I23: =IF(OR(Sales_Transactions!D7="North", Sales_Transactions!D7="South"), "Priority", "Standard") | J23: =IF(NOT(Sales_Transactions!Q7="Cancelled"), "Valid", "Excluded") | K23: =IFERROR(Sales_Transactions!O7/Sales_Transactions!M7, 0)
A24: 7 | B24: =Sales_Transactions!A8 | C24: =Sales_Transactions!C8 | D24: =Sales_Transactions!M8 | E24: =Sales_Transactions!Q8 | F24: =IF(Sales_Transactions!M8>=5000, "High Value", "Standard") | G24: =IF(Sales_Transactions!M8>=25000, "Tier 1", IF(Sales_Transactions!M8>=10000, "Tier 2", IF(Sales_Transactions!M8>=3000, "Tier 3", "Tier 4"))) | H24: =IF(AND(Sales_Transactions!M8>=5000, Sales_Transactions!Q8="Delivered"), "Bonus", "No") | I24: =IF(OR(Sales_Transactions!D8="North", Sales_Transactions!D8="South"), "Priority", "Standard") | J24: =IF(NOT(Sales_Transactions!Q8="Cancelled"), "Valid", "Excluded") | K24: =IFERROR(Sales_Transactions!O8/Sales_Transactions!M8, 0)
A25: 8 | B25: =Sales_Transactions!A9 | C25: =Sales_Transactions!C9 | D25: =Sales_Transactions!M9 | E25: =Sales_Transactions!Q9 | F25: =IF(Sales_Transactions!M9>=5000, "High Value", "Standard") | G25: =IF(Sales_Transactions!M9>=25000, "Tier 1", IF(Sales_Transactions!M9>=10000, "Tier 2", IF(Sales_Transactions!M9>=3000, "Tier 3", "Tier 4"))) | H25: =IF(AND(Sales_Transactions!M9>=5000, Sales_Transactions!Q9="Delivered"), "Bonus", "No") | I25: =IF(OR(Sales_Transactions!D9="North", Sales_Transactions!D9="South"), "Priority", "Standard") | J25: =IF(NOT(Sales_Transactions!Q9="Cancelled"), "Valid", "Excluded") | K25: =IFERROR(Sales_Transactions!O9/Sales_Transactions!M9, 0)
A26: 9 | B26: =Sales_Transactions!A10 | C26: =Sales_Transactions!C10 | D26: =Sales_Transactions!M10 | E26: =Sales_Transactions!Q10 | F26: =IF(Sales_Transactions!M10>=5000, "High Value", "Standard") | G26: =IF(Sales_Transactions!M10>=25000, "Tier 1", IF(Sales_Transactions!M10>=10000, "Tier 2", IF(Sales_Transactions!M10>=3000, "Tier 3", "Tier 4"))) | H26: =IF(AND(Sales_Transactions!M10>=5000, Sales_Transactions!Q10="Delivered"), "Bonus", "No") | I26: =IF(OR(Sales_Transactions!D10="North", Sales_Transactions!D10="South"), "Priority", "Standard") | J26: =IF(NOT(Sales_Transactions!Q10="Cancelled"), "Valid", "Excluded") | K26: =IFERROR(Sales_Transactions!O10/Sales_Transactions!M10, 0)
A27: 10 | B27: =Sales_Transactions!A11 | C27: =Sales_Transactions!C11 | D27: =Sales_Transactions!M11 | E27: =Sales_Transactions!Q11 | F27: =IF(Sales_Transactions!M11>=5000, "High Value", "Standard") | G27: =IF(Sales_Transactions!M11>=25000, "Tier 1", IF(Sales_Transactions!M11>=10000, "Tier 2", IF(Sales_Transactions!M11>=3000, "Tier 3", "Tier 4"))) | H27: =IF(AND(Sales_Transactions!M11>=5000, Sales_Transactions!Q11="Delivered"), "Bonus", "No") | I27: =IF(OR(Sales_Transactions!D11="North", Sales_Transactions!D11="South"), "Priority", "Standard") | J27: =IF(NOT(Sales_Transactions!Q11="Cancelled"), "Valid", "Excluded") | K27: =IFERROR(Sales_Transactions!O11/Sales_Transactions!M11, 0)
A28: 11 | B28: =Sales_Transactions!A12 | C28: =Sales_Transactions!C12 | D28: =Sales_Transactions!M12 | E28: =Sales_Transactions!Q12 | F28: =IF(Sales_Transactions!M12>=5000, "High Value", "Standard") | G28: =IF(Sales_Transactions!M12>=25000, "Tier 1", IF(Sales_Transactions!M12>=10000, "Tier 2", IF(Sales_Transactions!M12>=3000, "Tier 3", "Tier 4"))) | H28: =IF(AND(Sales_Transactions!M12>=5000, Sales_Transactions!Q12="Delivered"), "Bonus", "No") | I28: =IF(OR(Sales_Transactions!D12="North", Sales_Transactions!D12="South"), "Priority", "Standard") | J28: =IF(NOT(Sales_Transactions!Q12="Cancelled"), "Valid", "Excluded") | K28: =IFERROR(Sales_Transactions!O12/Sales_Transactions!M12, 0)
A29: 12 | B29: =Sales_Transactions!A13 | C29: =Sales_Transactions!C13 | D29: =Sales_Transactions!M13 | E29: =Sales_Transactions!Q13 | F29: =IF(Sales_Transactions!M13>=5000, "High Value", "Standard") | G29: =IF(Sales_Transactions!M13>=25000, "Tier 1", IF(Sales_Transactions!M13>=10000, "Tier 2", IF(Sales_Transactions!M13>=3000, "Tier 3", "Tier 4"))) | H29: =IF(AND(Sales_Transactions!M13>=5000, Sales_Transactions!Q13="Delivered"), "Bonus", "No") | I29: =IF(OR(Sales_Transactions!D13="North", Sales_Transactions!D13="South"), "Priority", "Standard") | J29: =IF(NOT(Sales_Transactions!Q13="Cancelled"), "Valid", "Excluded") | K29: =IFERROR(Sales_Transactions!O13/Sales_Transactions!M13, 0)
... A32: 15 | B32: =Sales_Transactions!A16 | C32: =Sales_Transactions!C16 | D32: =Sales_Transactions!M16 | E32: =Sales_Transactions!Q16 | F32: =IF(Sales_Transactions!M16>=5000, "High Value", "Standard") | G32: =IF(Sales_Transactions!M16>=25000, "Tier 1", IF(Sales_Transactions!M16>=10000, "Tier 2", IF(Sales_Transactions!M16>=3000, "Tier 3", "Tier 4"))) | H32: =IF(AND(Sales_Transactions!M16>=5000, Sales_Transactions!Q16="Delivered"), "Bonus", "No") | I32: =IF(OR(Sales_Transactions!D16="North", Sales_Transactions!D16="South"), "Priority", "Standard") | J32: =IF(NOT(Sales_Transactions!Q16="Cancelled"), "Valid", "Excluded") | K32: =IFERROR(Sales_Transactions!O16/Sales_Transactions!M16, 0)

Sheet Pivot_Summary_Matrix
A1: EXCEL PIVOT TABLE CROSS-TABULATION MATRIX (CATEGORY X REGION)
A3: Table 1: Net Revenue Cross-Tabulation Matrix (INR)
A4: Category | B4: Central | C4: East | D4: North | E4: South | F4: West | G4: Total Revenue
A5: Electronics | B5: =SUMIFS(Sales_Transactions!M:M, Sales_Transactions!G:G, "Electronics", Sales_Transactions!D:D, "Central", Sales_Transactions!Q:Q, "<>Cancelled") | C5: =SUMIFS(Sales_Transactions!M:M, Sales_Transactions!G:G, "Electronics", Sales_Transactions!D:D, "East", Sales_Transactions!Q:Q, "<>Cancelled") | D5: =SUMIFS(Sales_Transactions!M:M, Sales_Transactions!G:G, "Electronics", Sales_Transactions!D:D, "North", Sales_Transactions!Q:Q, "<>Cancelled") | E5: =SUMIFS(Sales_Transactions!M:M, Sales_Transactions!G:G, "Electronics", Sales_Transactions!D:D, "South", Sales_Transactions!Q:Q, "<>Cancelled") | F5: =SUMIFS(Sales_Transactions!M:M, Sales_Transactions!G:G, "Electronics", Sales_Transactions!D:D, "West", Sales_Transactions!Q:Q, "<>Cancelled") | G5: =SUM(B5:F5)
A6: Fashion | B6: =SUMIFS(Sales_Transactions!M:M, Sales_Transactions!G:G, "Fashion", Sales_Transactions!D:D, "Central", Sales_Transactions!Q:Q, "<>Cancelled") | C6: =SUMIFS(Sales_Transactions!M:M, Sales_Transactions!G:G, "Fashion", Sales_Transactions!D:D, "East", Sales_Transactions!Q:Q, "<>Cancelled") | D6: =SUMIFS(Sales_Transactions!M:M, Sales_Transactions!G:G, "Fashion", Sales_Transactions!D:D, "North", Sales_Transactions!Q:Q, "<>Cancelled") | E6: =SUMIFS(Sales_Transactions!M:M, Sales_Transactions!G:G, "Fashion", Sales_Transactions!D:D, "South", Sales_Transactions!Q:Q, "<>Cancelled") | F6: =SUMIFS(Sales_Transactions!M:M, Sales_Transactions!G:G, "Fashion", Sales_Transactions!D:D, "West", Sales_Transactions!Q:Q, "<>Cancelled") | G6: =SUM(B6:F6)
A7: Groceries | B7: =SUMIFS(Sales_Transactions!M:M, Sales_Transactions!G:G, "Groceries", Sales_Transactions!D:D, "Central", Sales_Transactions!Q:Q, "<>Cancelled") | C7: =SUMIFS(Sales_Transactions!M:M, Sales_Transactions!G:G, "Groceries", Sales_Transactions!D:D, "East", Sales_Transactions!Q:Q, "<>Cancelled") | D7: =SUMIFS(Sales_Transactions!M:M, Sales_Transactions!G:G, "Groceries", Sales_Transactions!D:D, "North", Sales_Transactions!Q:Q, "<>Cancelled") | E7: =SUMIFS(Sales_Transactions!M:M, Sales_Transactions!G:G, "Groceries", Sales_Transactions!D:D, "South", Sales_Transactions!Q:Q, "<>Cancelled") | F7: =SUMIFS(Sales_Transactions!M:M, Sales_Transactions!G:G, "Groceries", Sales_Transactions!D:D, "West", Sales_Transactions!Q:Q, "<>Cancelled") | G7: =SUM(B7:F7)
A8: Home & Living | B8: =SUMIFS(Sales_Transactions!M:M, Sales_Transactions!G:G, "Home & Living", Sales_Transactions!D:D, "Central", Sales_Transactions!Q:Q, "<>Cancelled") | C8: =SUMIFS(Sales_Transactions!M:M, Sales_Transactions!G:G, "Home & Living", Sales_Transactions!D:D, "East", Sales_Transactions!Q:Q, "<>Cancelled") | D8: =SUMIFS(Sales_Transactions!M:M, Sales_Transactions!G:G, "Home & Living", Sales_Transactions!D:D, "North", Sales_Transactions!Q:Q, "<>Cancelled") | E8: =SUMIFS(Sales_Transactions!M:M, Sales_Transactions!G:G, "Home & Living", Sales_Transactions!D:D, "South", Sales_Transactions!Q:Q, "<>Cancelled") | F8: =SUMIFS(Sales_Transactions!M:M, Sales_Transactions!G:G, "Home & Living", Sales_Transactions!D:D, "West", Sales_Transactions!Q:Q, "<>Cancelled") | G8: =SUM(B8:F8)
A9: Sports | B9: =SUMIFS(Sales_Transactions!M:M, Sales_Transactions!G:G, "Sports", Sales_Transactions!D:D, "Central", Sales_Transactions!Q:Q, "<>Cancelled") | C9: =SUMIFS(Sales_Transactions!M:M, Sales_Transactions!G:G, "Sports", Sales_Transactions!D:D, "East", Sales_Transactions!Q:Q, "<>Cancelled") | D9: =SUMIFS(Sales_Transactions!M:M, Sales_Transactions!G:G, "Sports", Sales_Transactions!D:D, "North", Sales_Transactions!Q:Q, "<>Cancelled") | E9: =SUMIFS(Sales_Transactions!M:M, Sales_Transactions!G:G, "Sports", Sales_Transactions!D:D, "South", Sales_Transactions!Q:Q, "<>Cancelled") | F9: =SUMIFS(Sales_Transactions!M:M, Sales_Transactions!G:G, "Sports", Sales_Transactions!D:D, "West", Sales_Transactions!Q:Q, "<>Cancelled") | G9: =SUM(B9:F9)
A10: Grand Total | B10: =SUM(B5:B9) | C10: =SUM(C5:C9) | D10: =SUM(D5:D9) | E10: =SUM(E5:E9) | F10: =SUM(F5:F9) | G10: =SUM(G5:G9)
A13: Table 2: Gross Profit Cross-Tabulation Matrix (INR)
A14: Category | B14: Central | C14: East | D14: North | E14: South | F14: West | G14: Total Profit
A15: Electronics | B15: =SUMIFS(Sales_Transactions!O:O, Sales_Transactions!G:G, "Electronics", Sales_Transactions!D:D, "Central", Sales_Transactions!Q:Q, "<>Cancelled") | C15: =SUMIFS(Sales_Transactions!O:O, Sales_Transactions!G:G, "Electronics", Sales_Transactions!D:D, "East", Sales_Transactions!Q:Q, "<>Cancelled") | D15: =SUMIFS(Sales_Transactions!O:O, Sales_Transactions!G:G, "Electronics", Sales_Transactions!D:D, "North", Sales_Transactions!Q:Q, "<>Cancelled") | E15: =SUMIFS(Sales_Transactions!O:O, Sales_Transactions!G:G, "Electronics", Sales_Transactions!D:D, "South", Sales_Transactions!Q:Q, "<>Cancelled") | F15: =SUMIFS(Sales_Transactions!O:O, Sales_Transactions!G:G, "Electronics", Sales_Transactions!D:D, "West", Sales_Transactions!Q:Q, "<>Cancelled") | G15: =SUM(B15:F15)
A16: Fashion | B16: =SUMIFS(Sales_Transactions!O:O, Sales_Transactions!G:G, "Fashion", Sales_Transactions!D:D, "Central", Sales_Transactions!Q:Q, "<>Cancelled") | C16: =SUMIFS(Sales_Transactions!O:O, Sales_Transactions!G:G, "Fashion", Sales_Transactions!D:D, "East", Sales_Transactions!Q:Q, "<>Cancelled") | D16: =SUMIFS(Sales_Transactions!O:O, Sales_Transactions!G:G, "Fashion", Sales_Transactions!D:D, "North", Sales_Transactions!Q:Q, "<>Cancelled") | E16: =SUMIFS(Sales_Transactions!O:O, Sales_Transactions!G:G, "Fashion", Sales_Transactions!D:D, "South", Sales_Transactions!Q:Q, "<>Cancelled") | F16: =SUMIFS(Sales_Transactions!O:O, Sales_Transactions!G:G, "Fashion", Sales_Transactions!D:D, "West", Sales_Transactions!Q:Q, "<>Cancelled") | G16: =SUM(B16:F16)
A17: Groceries | B17: =SUMIFS(Sales_Transactions!O:O, Sales_Transactions!G:G, "Groceries", Sales_Transactions!D:D, "Central", Sales_Transactions!Q:Q, "<>Cancelled") | C17: =SUMIFS(Sales_Transactions!O:O, Sales_Transactions!G:G, "Groceries", Sales_Transactions!D:D, "East", Sales_Transactions!Q:Q, "<>Cancelled") | D17: =SUMIFS(Sales_Transactions!O:O, Sales_Transactions!G:G, "Groceries", Sales_Transactions!D:D, "North", Sales_Transactions!Q:Q, "<>Cancelled") | E17: =SUMIFS(Sales_Transactions!O:O, Sales_Transactions!G:G, "Groceries", Sales_Transactions!D:D, "South", Sales_Transactions!Q:Q, "<>Cancelled") | F17: =SUMIFS(Sales_Transactions!O:O, Sales_Transactions!G:G, "Groceries", Sales_Transactions!D:D, "West", Sales_Transactions!Q:Q, "<>Cancelled") | G17: =SUM(B17:F17)
A18: Home & Living | B18: =SUMIFS(Sales_Transactions!O:O, Sales_Transactions!G:G, "Home & Living", Sales_Transactions!D:D, "Central", Sales_Transactions!Q:Q, "<>Cancelled") | C18: =SUMIFS(Sales_Transactions!O:O, Sales_Transactions!G:G, "Home & Living", Sales_Transactions!D:D, "East", Sales_Transactions!Q:Q, "<>Cancelled") | D18: =SUMIFS(Sales_Transactions!O:O, Sales_Transactions!G:G, "Home & Living", Sales_Transactions!D:D, "North", Sales_Transactions!Q:Q, "<>Cancelled") | E18: =SUMIFS(Sales_Transactions!O:O, Sales_Transactions!G:G, "Home & Living", Sales_Transactions!D:D, "South", Sales_Transactions!Q:Q, "<>Cancelled") | F18: =SUMIFS(Sales_Transactions!O:O, Sales_Transactions!G:G, "Home & Living", Sales_Transactions!D:D, "West", Sales_Transactions!Q:Q, "<>Cancelled") | G18: =SUM(B18:F18)
A19: Sports | B19: =SUMIFS(Sales_Transactions!O:O, Sales_Transactions!G:G, "Sports", Sales_Transactions!D:D, "Central", Sales_Transactions!Q:Q, "<>Cancelled") | C19: =SUMIFS(Sales_Transactions!O:O, Sales_Transactions!G:G, "Sports", Sales_Transactions!D:D, "East", Sales_Transactions!Q:Q, "<>Cancelled") | D19: =SUMIFS(Sales_Transactions!O:O, Sales_Transactions!G:G, "Sports", Sales_Transactions!D:D, "North", Sales_Transactions!Q:Q, "<>Cancelled") | E19: =SUMIFS(Sales_Transactions!O:O, Sales_Transactions!G:G, "Sports", Sales_Transactions!D:D, "South", Sales_Transactions!Q:Q, "<>Cancelled") | F19: =SUMIFS(Sales_Transactions!O:O, Sales_Transactions!G:G, "Sports", Sales_Transactions!D:D, "West", Sales_Transactions!Q:Q, "<>Cancelled") | G19: =SUM(B19:F19)
A20: Grand Total | B20: =SUM(B15:B19) | C20: =SUM(C15:C19) | D20: =SUM(D15:D19) | E20: =SUM(E15:E19) | F20: =SUM(F15:F19) | G20: =SUM(G15:G19)

Sheet Customer_Lifetime_Value
A1: CUSTOMER LIFETIME VALUE (CLV) & SEGMENTATION DIRECTORY
A4: Customer ID | B4: Customer Name | C4: City | D4: Region | E4: Total Orders | F4: Lifetime Spend (INR) | G4: Last Order Date | H4: Loyalty Tier
A5: 1 | B5: Pooja Sharma | C5: Pune | D5: West | E5: =COUNTIFS(Sales_Transactions!C:C, "Pooja Sharma", Sales_Transactions!Q:Q, "<>Cancelled") | F5: =SUMIFS(Sales_Transactions!M:M, Sales_Transactions!C:C, "Pooja Sharma", Sales_Transactions!Q:Q, "<>Cancelled") | G5: =IF(E5=0, "Never Purchased", "Active Customer") | H5: =IF(E5=0, "Inactive", IF(F5>=50000, "Platinum", IF(F5>=20000, "Gold", IF(F5>=5000, "Silver", "Bronze"))))
A6: 2 | B6: Amit Iyer | C6: Bhopal | D6: Central | E6: =COUNTIFS(Sales_Transactions!C:C, "Amit Iyer", Sales_Transactions!Q:Q, "<>Cancelled") | F6: =SUMIFS(Sales_Transactions!M:M, Sales_Transactions!C:C, "Amit Iyer", Sales_Transactions!Q:Q, "<>Cancelled") | G6: =IF(E6=0, "Never Purchased", "Active Customer") | H6: =IF(E6=0, "Inactive", IF(F6>=50000, "Platinum", IF(F6>=20000, "Gold", IF(F6>=5000, "Silver", "Bronze"))))
A7: 3 | B7: Rohit Sharma | C7: Noida | D7: North | E7: =COUNTIFS(Sales_Transactions!C:C, "Rohit Sharma", Sales_Transactions!Q:Q, "<>Cancelled") | F7: =SUMIFS(Sales_Transactions!M:M, Sales_Transactions!C:C, "Rohit Sharma", Sales_Transactions!Q:Q, "<>Cancelled") | G7: =IF(E7=0, "Never Purchased", "Active Customer") | H7: =IF(E7=0, "Inactive", IF(F7>=50000, "Platinum", IF(F7>=20000, "Gold", IF(F7>=5000, "Silver", "Bronze"))))
A8: 4 | B8: Rhea Kulkarni | C8: Jaipur | D8: North | E8: =COUNTIFS(Sales_Transactions!C:C, "Rhea Kulkarni", Sales_Transactions!Q:Q, "<>Cancelled") | F8: =SUMIFS(Sales_Transactions!M:M, Sales_Transactions!C:C, "Rhea Kulkarni", Sales_Transactions!Q:Q, "<>Cancelled") | G8: =IF(E8=0, "Never Purchased", "Active Customer") | H8: =IF(E8=0, "Inactive", IF(F8>=50000, "Platinum", IF(F8>=20000, "Gold", IF(F8>=5000, "Silver", "Bronze"))))
A9: 5 | B9: Nandini Joshi | C9: Kochi | D9: South | E9: =COUNTIFS(Sales_Transactions!C:C, "Nandini Joshi", Sales_Transactions!Q:Q, "<>Cancelled") | F9: =SUMIFS(Sales_Transactions!M:M, Sales_Transactions!C:C, "Nandini Joshi", Sales_Transactions!Q:Q, "<>Cancelled") | G9: =IF(E9=0, "Never Purchased", "Active Customer") | H9: =IF(E9=0, "Inactive", IF(F9>=50000, "Platinum", IF(F9>=20000, "Gold", IF(F9>=5000, "Silver", "Bronze"))))
A10: 6 | B10: Aarav Rao | C10: Patna | D10: East | E10: =COUNTIFS(Sales_Transactions!C:C, "Aarav Rao", Sales_Transactions!Q:Q, "<>Cancelled") | F10: =SUMIFS(Sales_Transactions!M:M, Sales_Transactions!C:C, "Aarav Rao", Sales_Transactions!Q:Q, "<>Cancelled") | G10: =IF(E10=0, "Never Purchased", "Active Customer") | H10: =IF(E10=0, "Inactive", IF(F10>=50000, "Platinum", IF(F10>=20000, "Gold", IF(F10>=5000, "Silver", "Bronze"))))
A11: 7 | B11: Kavita Nair | C11: Mumbai | D11: West | E11: =COUNTIFS(Sales_Transactions!C:C, "Kavita Nair", Sales_Transactions!Q:Q, "<>Cancelled") | F11: =SUMIFS(Sales_Transactions!M:M, Sales_Transactions!C:C, "Kavita Nair", Sales_Transactions!Q:Q, "<>Cancelled") | G11: =IF(E11=0, "Never Purchased", "Active Customer") | H11: =IF(E11=0, "Inactive", IF(F11>=50000, "Platinum", IF(F11>=20000, "Gold", IF(F11>=5000, "Silver", "Bronze"))))
A12: 8 | B12: Gaurav Iyer | C12: Ahmedabad | D12: West | E12: =COUNTIFS(Sales_Transactions!C:C, "Gaurav Iyer", Sales_Transactions!Q:Q, "<>Cancelled") | F12: =SUMIFS(Sales_Transactions!M:M, Sales_Transactions!C:C, "Gaurav Iyer", Sales_Transactions!Q:Q, "<>Cancelled") | G12: =IF(E12=0, "Never Purchased", "Active Customer") | H12: =IF(E12=0, "Inactive", IF(F12>=50000, "Platinum", IF(F12>=20000, "Gold", IF(F12>=5000, "Silver", "Bronze"))))
A13: 9 | B13: Rohit Bhat | C13: Bhopal | D13: Central | E13: =COUNTIFS(Sales_Transactions!C:C, "Rohit Bhat", Sales_Transactions!Q:Q, "<>Cancelled") | F13: =SUMIFS(Sales_Transactions!M:M, Sales_Transactions!C:C, "Rohit Bhat", Sales_Transactions!Q:Q, "<>Cancelled") | G13: =IF(E13=0, "Never Purchased", "Active Customer") | H13: =IF(E13=0, "Inactive", IF(F13>=50000, "Platinum", IF(F13>=20000, "Gold", IF(F13>=5000, "Silver", "Bronze"))))
A14: 10 | B14: Sneha Saxena | C14: Nagpur | D14: West | E14: =COUNTIFS(Sales_Transactions!C:C, "Sneha Saxena", Sales_Transactions!Q:Q, "<>Cancelled") | F14: =SUMIFS(Sales_Transactions!M:M, Sales_Transactions!C:C, "Sneha Saxena", Sales_Transactions!Q:Q, "<>Cancelled") | G14: =IF(E14=0, "Never Purchased", "Active Customer") | H14: =IF(E14=0, "Inactive", IF(F14>=50000, "Platinum", IF(F14>=20000, "Gold", IF(F14>=5000, "Silver", "Bronze"))))
A15: 11 | B15: Bhavna Nair | C15: Delhi | D15: North | E15: =COUNTIFS(Sales_Transactions!C:C, "Bhavna Nair", Sales_Transactions!Q:Q, "<>Cancelled") | F15: =SUMIFS(Sales_Transactions!M:M, Sales_Transactions!C:C, "Bhavna Nair", Sales_Transactions!Q:Q, "<>Cancelled") | G15: =IF(E15=0, "Never Purchased", "Active Customer") | H15: =IF(E15=0, "Inactive", IF(F15>=50000, "Platinum", IF(F15>=20000, "Gold", IF(F15>=5000, "Silver", "Bronze"))))
A16: 12 | B16: Aditya Verma | C16: Bengaluru | D16: South | E16: =COUNTIFS(Sales_Transactions!C:C, "Aditya Verma", Sales_Transactions!Q:Q, "<>Cancelled") | F16: =SUMIFS(Sales_Transactions!M:M, Sales_Transactions!C:C, "Aditya Verma", Sales_Transactions!Q:Q, "<>Cancelled") | G16: =IF(E16=0, "Never Purchased", "Active Customer") | H16: =IF(E16=0, "Inactive", IF(F16>=50000, "Platinum", IF(F16>=20000, "Gold", IF(F16>=5000, "Silver", "Bronze"))))
A17: 13 | B17: Meera Bhat | C17: Pune | D17: West | E17: =COUNTIFS(Sales_Transactions!C:C, "Meera Bhat", Sales_Transactions!Q:Q, "<>Cancelled") | F17: =SUMIFS(Sales_Transactions!M:M, Sales_Transactions!C:C, "Meera Bhat", Sales_Transactions!Q:Q, "<>Cancelled") | G17: =IF(E17=0, "Never Purchased", "Active Customer") | H17: =IF(E17=0, "Inactive", IF(F17>=50000, "Platinum", IF(F17>=20000, "Gold", IF(F17>=5000, "Silver", "Bronze"))))
A18: 14 | B18: Sunil Nair | C18: Mumbai | D18: West | E18: =COUNTIFS(Sales_Transactions!C:C, "Sunil Nair", Sales_Transactions!Q:Q, "<>Cancelled") | F18: =SUMIFS(Sales_Transactions!M:M, Sales_Transactions!C:C, "Sunil Nair", Sales_Transactions!Q:Q, "<>Cancelled") | G18: =IF(E18=0, "Never Purchased", "Active Customer") | H18: =IF(E18=0, "Inactive", IF(F18>=50000, "Platinum", IF(F18>=20000, "Gold", IF(F18>=5000, "Silver", "Bronze"))))
A19: 15 | B19: Nandini Gupta | C19: Kochi | D19: South | E19: =COUNTIFS(Sales_Transactions!C:C, "Nandini Gupta", Sales_Transactions!Q:Q, "<>Cancelled") | F19: =SUMIFS(Sales_Transactions!M:M, Sales_Transactions!C:C, "Nandini Gupta", Sales_Transactions!Q:Q, "<>Cancelled") | G19: =IF(E19=0, "Never Purchased", "Active Customer") | H19: =IF(E19=0, "Inactive", IF(F19>=50000, "Platinum", IF(F19>=20000, "Gold", IF(F19>=5000, "Silver", "Bronze"))))
A20: 16 | B20: Meera Saxena | C20: Hyderabad | D20: South | E20: =COUNTIFS(Sales_Transactions!C:C, "Meera Saxena", Sales_Transactions!Q:Q, "<>Cancelled") | F20: =SUMIFS(Sales_Transactions!M:M, Sales_Transactions!C:C, "Meera Saxena", Sales_Transactions!Q:Q, "<>Cancelled") | G20: =IF(E20=0, "Never Purchased", "Active Customer") | H20: =IF(E20=0, "Inactive", IF(F20>=50000, "Platinum", IF(F20>=20000, "Gold", IF(F20>=5000, "Silver", "Bronze"))))
A21: 17 | B21: Manoj Patel | C21: Surat | D21: West | E21: =COUNTIFS(Sales_Transactions!C:C, "Manoj Patel", Sales_Transactions!Q:Q, "<>Cancelled") | F21: =SUMIFS(Sales_Transactions!M:M, Sales_Transactions!C:C, "Manoj Patel", Sales_Transactions!Q:Q, "<>Cancelled") | G21: =IF(E21=0, "Never Purchased", "Active Customer") | H21: =IF(E21=0, "Inactive", IF(F21>=50000, "Platinum", IF(F21>=20000, "Gold", IF(F21>=5000, "Silver", "Bronze"))))
A22: 18 | B22: Vikram Nair | C22: Raipur | D22: Central | E22: =COUNTIFS(Sales_Transactions!C:C, "Vikram Nair", Sales_Transactions!Q:Q, "<>Cancelled") | F22: =SUMIFS(Sales_Transactions!M:M, Sales_Transactions!C:C, "Vikram Nair", Sales_Transactions!Q:Q, "<>Cancelled") | G22: =IF(E22=0, "Never Purchased", "Active Customer") | H22: =IF(E22=0, "Inactive", IF(F22>=50000, "Platinum", IF(F22>=20000, "Gold", IF(F22>=5000, "Silver", "Bronze"))))
A23: 19 | B23: Ishaan Banerjee | C23: Bhubaneswar | D23: East | E23: =COUNTIFS(Sales_Transactions!C:C, "Ishaan Banerjee", Sales_Transactions!Q:Q, "<>Cancelled") | F23: =SUMIFS(Sales_Transactions!M:M, Sales_Transactions!C:C, "Ishaan Banerjee", Sales_Transactions!Q:Q, "<>Cancelled") | G23: =IF(E23=0, "Never Purchased", "Active Customer") | H23: =IF(E23=0, "Inactive", IF(F23>=50000, "Platinum", IF(F23>=20000, "Gold", IF(F23>=5000, "Silver", "Bronze"))))
A24: 20 | B24: Amit Gupta | C24: Gwalior | D24: Central | E24: =COUNTIFS(Sales_Transactions!C:C, "Amit Gupta", Sales_Transactions!Q:Q, "<>Cancelled") | F24: =SUMIFS(Sales_Transactions!M:M, Sales_Transactions!C:C, "Amit Gupta", Sales_Transactions!Q:Q, "<>Cancelled") | G24: =IF(E24=0, "Never Purchased", "Active Customer") | H24: =IF(E24=0, "Inactive", IF(F24>=50000, "Platinum", IF(F24>=20000, "Gold", IF(F24>=5000, "Silver", "Bronze"))))
A25: 21 | B25: Kiran Joshi | C25: Jabalpur | D25: Central | E25: =COUNTIFS(Sales_Transactions!C:C, "Kiran Joshi", Sales_Transactions!Q:Q, "<>Cancelled") | F25: =SUMIFS(Sales_Transactions!M:M, Sales_Transactions!C:C, "Kiran Joshi", Sales_Transactions!Q:Q, "<>Cancelled") | G25: =IF(E25=0, "Never Purchased", "Active Customer") | H25: =IF(E25=0, "Inactive", IF(F25>=50000, "Platinum", IF(F25>=20000, "Gold", IF(F25>=5000, "Silver", "Bronze"))))
A26: 22 | B26: Manoj Singh | C26: Jabalpur | D26: Central | E26: =COUNTIFS(Sales_Transactions!C:C, "Manoj Singh", Sales_Transactions!Q:Q, "<>Cancelled") | F26: =SUMIFS(Sales_Transactions!M:M, Sales_Transactions!C:C, "Manoj Singh", Sales_Transactions!Q:Q, "<>Cancelled") | G26: =IF(E26=0, "Never Purchased", "Active Customer") | H26: =IF(E26=0, "Inactive", IF(F26>=50000, "Platinum", IF(F26>=20000, "Gold", IF(F26>=5000, "Silver", "Bronze"))))
A27: 23 | B27: Ananya Iyer | C27: Chennai | D27: South | E27: =COUNTIFS(Sales_Transactions!C:C, "Ananya Iyer", Sales_Transactions!Q:Q, "<>Cancelled") | F27: =SUMIFS(Sales_Transactions!M:M, Sales_Transactions!C:C, "Ananya Iyer", Sales_Transactions!Q:Q, "<>Cancelled") | G27: =IF(E27=0, "Never Purchased", "Active Customer") | H27: =IF(E27=0, "Inactive", IF(F27>=50000, "Platinum", IF(F27>=20000, "Gold", IF(F27>=5000, "Silver", "Bronze"))))
A28: 24 | B28: Vidya Verma | C28: Ranchi | D28: East | E28: =COUNTIFS(Sales_Transactions!C:C, "Vidya Verma", Sales_Transactions!Q:Q, "<>Cancelled") | F28: =SUMIFS(Sales_Transactions!M:M, Sales_Transactions!C:C, "Vidya Verma", Sales_Transactions!Q:Q, "<>Cancelled") | G28: =IF(E28=0, "Never Purchased", "Active Customer") | H28: =IF(E28=0, "Inactive", IF(F28>=50000, "Platinum", IF(F28>=20000, "Gold", IF(F28>=5000, "Silver", "Bronze"))))
A29: 25 | B29: Alok Deshmukh | C29: Bhopal | D29: Central | E29: =COUNTIFS(Sales_Transactions!C:C, "Alok Deshmukh", Sales_Transactions!Q:Q, "<>Cancelled") | F29: =SUMIFS(Sales_Transactions!M:M, Sales_Transactions!C:C, "Alok Deshmukh", Sales_Transactions!Q:Q, "<>Cancelled") | G29: =IF(E29=0, "Never Purchased", "Active Customer") | H29: =IF(E29=0, "Inactive", IF(F29>=50000, "Platinum", IF(F29>=20000, "Gold", IF(F29>=5000, "Silver", "Bronze"))))
A30: 26 | B30: Nandini Deshmukh | C30: Mumbai | D30: West | E30: =COUNTIFS(Sales_Transactions!C:C, "Nandini Deshmukh", Sales_Transactions!Q:Q, "<>Cancelled") | F30: =SUMIFS(Sales_Transactions!M:M, Sales_Transactions!C:C, "Nandini Deshmukh", Sales_Transactions!Q:Q, "<>Cancelled") | G30: =IF(E30=0, "Never Purchased", "Active Customer") | H30: =IF(E30=0, "Inactive", IF(F30>=50000, "Platinum", IF(F30>=20000, "Gold", IF(F30>=5000, "Silver", "Bronze"))))
A31: 27 | B31: Anjali Rao | C31: Kolkata | D31: East | E31: =COUNTIFS(Sales_Transactions!C:C, "Anjali Rao", Sales_Transactions!Q:Q, "<>Cancelled") | F31: =SUMIFS(Sales_Transactions!M:M, Sales_Transactions!C:C, "Anjali Rao", Sales_Transactions!Q:Q, "<>Cancelled") | G31: =IF(E31=0, "Never Purchased", "Active Customer") | H31: =IF(E31=0, "Inactive", IF(F31>=50000, "Platinum", IF(F31>=20000, "Gold", IF(F31>=5000, "Silver", "Bronze"))))
A32: 28 | B32: Rhea Rao | C32: Bhopal | D32: Central | E32: =COUNTIFS(Sales_Transactions!C:C, "Rhea Rao", Sales_Transactions!Q:Q, "<>Cancelled") | F32: =SUMIFS(Sales_Transactions!M:M, Sales_Transactions!C:C, "Rhea Rao", Sales_Transactions!Q:Q, "<>Cancelled") | G32: =IF(E32=0, "Never Purchased", "Active Customer") | H32: =IF(E32=0, "Inactive", IF(F32>=50000, "Platinum", IF(F32>=20000, "Gold", IF(F32>=5000, "Silver", "Bronze"))))
A33: 29 | B33: Rhea Kulkarni | C33: Chennai | D33: South | E33: =COUNTIFS(Sales_Transactions!C:C, "Rhea Kulkarni", Sales_Transactions!Q:Q, "<>Cancelled") | F33: =SUMIFS(Sales_Transactions!M:M, Sales_Transactions!C:C, "Rhea Kulkarni", Sales_Transactions!Q:Q, "<>Cancelled") | G33: =IF(E33=0, "Never Purchased", "Active Customer") | H33: =IF(E33=0, "Inactive", IF(F33>=50000, "Platinum", IF(F33>=20000, "Gold", IF(F33>=5000, "Silver", "Bronze"))))
A34: 30 | B34: Suresh Saxena | C34: Bhopal | D34: Central | E34: =COUNTIFS(Sales_Transactions!C:C, "Suresh Saxena", Sales_Transactions!Q:Q, "<>Cancelled") | F34: =SUMIFS(Sales_Transactions!M:M, Sales_Transactions!C:C, "Suresh Saxena", Sales_Transactions!Q:Q, "<>Cancelled") | G34: =IF(E34=0, "Never Purchased", "Active Customer") | H34: =IF(E34=0, "Inactive", IF(F34>=50000, "Platinum", IF(F34>=20000, "Gold", IF(F34>=5000, "Silver", "Bronze"))))
A35: 31 | B35: Ishaan Sharma | C35: Gurgaon | D35: North | E35: =COUNTIFS(Sales_Transactions!C:C, "Ishaan Sharma", Sales_Transactions!Q:Q, "<>Cancelled") | F35: =SUMIFS(Sales_Transactions!M:M, Sales_Transactions!C:C, "Ishaan Sharma", Sales_Transactions!Q:Q, "<>Cancelled") | G35: =IF(E35=0, "Never Purchased", "Active Customer") | H35: =IF(E35=0, "Inactive", IF(F35>=50000, "Platinum", IF(F35>=20000, "Gold", IF(F35>=5000, "Silver", "Bronze"))))
A36: 32 | B36: Shreya Patel | C36: Coimbatore | D36: South | E36: =COUNTIFS(Sales_Transactions!C:C, "Shreya Patel", Sales_Transactions!Q:Q, "<>Cancelled") | F36: =SUMIFS(Sales_Transactions!M:M, Sales_Transactions!C:C, "Shreya Patel", Sales_Transactions!Q:Q, "<>Cancelled") | G36: =IF(E36=0, "Never Purchased", "Active Customer") | H36: =IF(E36=0, "Inactive", IF(F36>=50000, "Platinum", IF(F36>=20000, "Gold", IF(F36>=5000, "Silver", "Bronze"))))
A37: 33 | B37: Sneha Kapoor | C37: Jaipur | D37: North | E37: =COUNTIFS(Sales_Transactions!C:C, "Sneha Kapoor", Sales_Transactions!Q:Q, "<>Cancelled") | F37: =SUMIFS(Sales_Transactions!M:M, Sales_Transactions!C:C, "Sneha Kapoor", Sales_Transactions!Q:Q, "<>Cancelled") | G37: =IF(E37=0, "Never Purchased", "Active Customer") | H37: =IF(E37=0, "Inactive", IF(F37>=50000, "Platinum", IF(F37>=20000, "Gold", IF(F37>=5000, "Silver", "Bronze"))))
A38: 34 | B38: Amit Kapoor | C38: Indore | D38: Central | E38: =COUNTIFS(Sales_Transactions!C:C, "Amit Kapoor", Sales_Transactions!Q:Q, "<>Cancelled") | F38: =SUMIFS(Sales_Transactions!M:M, Sales_Transactions!C:C, "Amit Kapoor", Sales_Transactions!Q:Q, "<>Cancelled") | G38: =IF(E38=0, "Never Purchased", "Active Customer") | H38: =IF(E38=0, "Inactive", IF(F38>=50000, "Platinum", IF(F38>=20000, "Gold", IF(F38>=5000, "Silver", "Bronze"))))
A39: 35 | B39: Alok Kulkarni | C39: Bhubaneswar | D39: East | E39: =COUNTIFS(Sales_Transactions!C:C, "Alok Kulkarni", Sales_Transactions!Q:Q, "<>Cancelled") | F39: =SUMIFS(Sales_Transactions!M:M, Sales_Transactions!C:C, "Alok Kulkarni", Sales_Transactions!Q:Q, "<>Cancelled") | G39: =IF(E39=0, "Never Purchased", "Active Customer") | H39: =IF(E39=0, "Inactive", IF(F39>=50000, "Platinum", IF(F39>=20000, "Gold", IF(F39>=5000, "Silver", "Bronze"))))
A40: 36 | B40: Arjun Choudhury | C40: Patna | D40: East | E40: =COUNTIFS(Sales_Transactions!C:C, "Arjun Choudhury", Sales_Transactions!Q:Q, "<>Cancelled") | F40: =SUMIFS(Sales_Transactions!M:M, Sales_Transactions!C:C, "Arjun Choudhury", Sales_Transactions!Q:Q, "<>Cancelled") | G40: =IF(E40=0, "Never Purchased", "Active Customer") | H40: =IF(E40=0, "Inactive", IF(F40>=50000, "Platinum", IF(F40>=20000, "Gold", IF(F40>=5000, "Silver", "Bronze"))))
A41: 37 | B41: Alok Bhat | C41: Noida | D41: North | E41: =COUNTIFS(Sales_Transactions!C:C, "Alok Bhat", Sales_Transactions!Q:Q, "<>Cancelled") | F41: =SUMIFS(Sales_Transactions!M:M, Sales_Transactions!C:C, "Alok Bhat", Sales_Transactions!Q:Q, "<>Cancelled") | G41: =IF(E41=0, "Never Purchased", "Active Customer") | H41: =IF(E41=0, "Inactive", IF(F41>=50000, "Platinum", IF(F41>=20000, "Gold", IF(F41>=5000, "Silver", "Bronze"))))
A42: 38 | B42: Vikram Reddy | C42: Jaipur | D42: North | E42: =COUNTIFS(Sales_Transactions!C:C, "Vikram Reddy", Sales_Transactions!Q:Q, "<>Cancelled") | F42: =SUMIFS(Sales_Transactions!M:M, Sales_Transactions!C:C, "Vikram Reddy", Sales_Transactions!Q:Q, "<>Cancelled") | G42: =IF(E42=0, "Never Purchased", "Active Customer") | H42: =IF(E42=0, "Inactive", IF(F42>=50000, "Platinum", IF(F42>=20000, "Gold", IF(F42>=5000, "Silver", "Bronze"))))
A43: 39 | B43: Kiran Gupta | C43: Delhi | D43: North | E43: =COUNTIFS(Sales_Transactions!C:C, "Kiran Gupta", Sales_Transactions!Q:Q, "<>Cancelled") | F43: =SUMIFS(Sales_Transactions!M:M, Sales_Transactions!C:C, "Kiran Gupta", Sales_Transactions!Q:Q, "<>Cancelled") | G43: =IF(E43=0, "Never Purchased", "Active Customer") | H43: =IF(E43=0, "Inactive", IF(F43>=50000, "Platinum", IF(F43>=20000, "Gold", IF(F43>=5000, "Silver", "Bronze"))))
A44: 40 | B44: Manoj Verma | C44: Gurgaon | D44: North | E44: =COUNTIFS(Sales_Transactions!C:C, "Manoj Verma", Sales_Transactions!Q:Q, "<>Cancelled") | F44: =SUMIFS(Sales_Transactions!M:M, Sales_Transactions!C:C, "Manoj Verma", Sales_Transactions!Q:Q, "<>Cancelled") | G44: =IF(E44=0, "Never Purchased", "Active Customer") | H44: =IF(E44=0, "Inactive", IF(F44>=50000, "Platinum", IF(F44>=20000, "Gold", IF(F44>=5000, "Silver", "Bronze"))))
A45: 41 | B45: Rhea Gupta | C45: Surat | D45: West | E45: =COUNTIFS(Sales_Transactions!C:C, "Rhea Gupta", Sales_Transactions!Q:Q, "<>Cancelled") | F45: =SUMIFS(Sales_Transactions!M:M, Sales_Transactions!C:C, "Rhea Gupta", Sales_Transactions!Q:Q, "<>Cancelled") | G45: =IF(E45=0, "Never Purchased", "Active Customer") | H45: =IF(E45=0, "Inactive", IF(F45>=50000, "Platinum", IF(F45>=20000, "Gold", IF(F45>=5000, "Silver", "Bronze"))))
A46: 42 | B46: Nandini Singh | C46: Gwalior | D46: Central | E46: =COUNTIFS(Sales_Transactions!C:C, "Nandini Singh", Sales_Transactions!Q:Q, "<>Cancelled") | F46: =SUMIFS(Sales_Transactions!M:M, Sales_Transactions!C:C, "Nandini Singh", Sales_Transactions!Q:Q, "<>Cancelled") | G46: =IF(E46=0, "Never Purchased", "Active Customer") | H46: =IF(E46=0, "Inactive", IF(F46>=50000, "Platinum", IF(F46>=20000, "Gold", IF(F46>=5000, "Silver", "Bronze"))))
A47: 43 | B47: Shreya Kapoor | C47: Bhubaneswar | D47: East | E47: =COUNTIFS(Sales_Transactions!C:C, "Shreya Kapoor", Sales_Transactions!Q:Q, "<>Cancelled") | F47: =SUMIFS(Sales_Transactions!M:M, Sales_Transactions!C:C, "Shreya Kapoor", Sales_Transactions!Q:Q, "<>Cancelled") | G47: =IF(E47=0, "Never Purchased", "Active Customer") | H47: =IF(E47=0, "Inactive", IF(F47>=50000, "Platinum", IF(F47>=20000, "Gold", IF(F47>=5000, "Silver", "Bronze"))))
A48: 44 | B48: Rajesh Joshi | C48: Surat | D48: West | E48: =COUNTIFS(Sales_Transactions!C:C, "Rajesh Joshi", Sales_Transactions!Q:Q, "<>Cancelled") | F48: =SUMIFS(Sales_Transactions!M:M, Sales_Transactions!C:C, "Rajesh Joshi", Sales_Transactions!Q:Q, "<>Cancelled") | G48: =IF(E48=0, "Never Purchased", "Active Customer") | H48: =IF(E48=0, "Inactive", IF(F48>=50000, "Platinum", IF(F48>=20000, "Gold", IF(F48>=5000, "Silver", "Bronze"))))
A49: 45 | B49: Simran Patel | C49: Delhi | D49: North | E49: =COUNTIFS(Sales_Transactions!C:C, "Simran Patel", Sales_Transactions!Q:Q, "<>Cancelled") | F49: =SUMIFS(Sales_Transactions!M:M, Sales_Transactions!C:C, "Simran Patel", Sales_Transactions!Q:Q, "<>Cancelled") | G49: =IF(E49=0, "Never Purchased", "Active Customer") | H49: =IF(E49=0, "Inactive", IF(F49>=50000, "Platinum", IF(F49>=20000, "Gold", IF(F49>=5000, "Silver", "Bronze"))))
A50: 46 | B50: Deepika Iyer | C50: Chennai | D50: South | E50: =COUNTIFS(Sales_Transactions!C:C, "Deepika Iyer", Sales_Transactions!Q:Q, "<>Cancelled") | F50: =SUMIFS(Sales_Transactions!M:M, Sales_Transactions!C:C, "Deepika Iyer", Sales_Transactions!Q:Q, "<>Cancelled") | G50: =IF(E50=0, "Never Purchased", "Active Customer") | H50: =IF(E50=0, "Inactive", IF(F50>=50000, "Platinum", IF(F50>=20000, "Gold", IF(F50>=5000, "Silver", "Bronze"))))
A51: 47 | B51: Nandini Bhat | C51: Kochi | D51: South | E51: =COUNTIFS(Sales_Transactions!C:C, "Nandini Bhat", Sales_Transactions!Q:Q, "<>Cancelled") | F51: =SUMIFS(Sales_Transactions!M:M, Sales_Transactions!C:C, "Nandini Bhat", Sales_Transactions!Q:Q, "<>Cancelled") | G51: =IF(E51=0, "Never Purchased", "Active Customer") | H51: =IF(E51=0, "Inactive", IF(F51>=50000, "Platinum", IF(F51>=20000, "Gold", IF(F51>=5000, "Silver", "Bronze"))))
A52: 48 | B52: Meera Bhat | C52: Bengaluru | D52: South | E52: =COUNTIFS(Sales_Transactions!C:C, "Meera Bhat", Sales_Transactions!Q:Q, "<>Cancelled") | F52: =SUMIFS(Sales_Transactions!M:M, Sales_Transactions!C:C, "Meera Bhat", Sales_Transactions!Q:Q, "<>Cancelled") | G52: =IF(E52=0, "Never Purchased", "Active Customer") | H52: =IF(E52=0, "Inactive", IF(F52>=50000, "Platinum", IF(F52>=20000, "Gold", IF(F52>=5000, "Silver", "Bronze"))))
A53: 49 | B53: Harsh Iyer | C53: Lucknow | D53: North | E53: =COUNTIFS(Sales_Transactions!C:C, "Harsh Iyer", Sales_Transactions!Q:Q, "<>Cancelled") | F53: =SUMIFS(Sales_Transactions!M:M, Sales_Transactions!C:C, "Harsh Iyer", Sales_Transactions!Q:Q, "<>Cancelled") | G53: =IF(E53=0, "Never Purchased", "Active Customer") | H53: =IF(E53=0, "Inactive", IF(F53>=50000, "Platinum", IF(F53>=20000, "Gold", IF(F53>=5000, "Silver", "Bronze"))))
A54: 50 | B54: Aarav Verma | C54: Chennai | D54: South | E54: =COUNTIFS(Sales_Transactions!C:C, "Aarav Verma", Sales_Transactions!Q:Q, "<>Cancelled") | F54: =SUMIFS(Sales_Transactions!M:M, Sales_Transactions!C:C, "Aarav Verma", Sales_Transactions!Q:Q, "<>Cancelled") | G54: =IF(E54=0, "Never Purchased", "Active Customer") | H54: =IF(E54=0, "Inactive", IF(F54>=50000, "Platinum", IF(F54>=20000, "Gold", IF(F54>=5000, "Silver", "Bronze"))))
A55: 51 | B55: Ishaan Kapoor | C55: Kochi | D55: South | E55: =COUNTIFS(Sales_Transactions!C:C, "Ishaan Kapoor", Sales_Transactions!Q:Q, "<>Cancelled") | F55: =SUMIFS(Sales_Transactions!M:M, Sales_Transactions!C:C, "Ishaan Kapoor", Sales_Transactions!Q:Q, "<>Cancelled") | G55: =IF(E55=0, "Never Purchased", "Active Customer") | H55: =IF(E55=0, "Inactive", IF(F55>=50000, "Platinum", IF(F55>=20000, "Gold", IF(F55>=5000, "Silver", "Bronze"))))
A56: 52 | B56: Suresh Banerjee | C56: Chandigarh | D56: North | E56: =COUNTIFS(Sales_Transactions!C:C, "Suresh Banerjee", Sales_Transactions!Q:Q, "<>Cancelled") | F56: =SUMIFS(Sales_Transactions!M:M, Sales_Transactions!C:C, "Suresh Banerjee", Sales_Transactions!Q:Q, "<>Cancelled") | G56: =IF(E56=0, "Never Purchased", "Active Customer") | H56: =IF(E56=0, "Inactive", IF(F56>=50000, "Platinum", IF(F56>=20000, "Gold", IF(F56>=5000, "Silver", "Bronze"))))
A57: 53 | B57: Simran Choudhury | C57: Guwahati | D57: East | E57: =COUNTIFS(Sales_Transactions!C:C, "Simran Choudhury", Sales_Transactions!Q:Q, "<>Cancelled") | F57: =SUMIFS(Sales_Transactions!M:M, Sales_Transactions!C:C, "Simran Choudhury", Sales_Transactions!Q:Q, "<>Cancelled") | G57: =IF(E57=0, "Never Purchased", "Active Customer") | H57: =IF(E57=0, "Inactive", IF(F57>=50000, "Platinum", IF(F57>=20000, "Gold", IF(F57>=5000, "Silver", "Bronze"))))
A58: 54 | B58: Kavita Nair | C58: Pune | D58: West | E58: =COUNTIFS(Sales_Transactions!C:C, "Kavita Nair", Sales_Transactions!Q:Q, "<>Cancelled") | F58: =SUMIFS(Sales_Transactions!M:M, Sales_Transactions!C:C, "Kavita Nair", Sales_Transactions!Q:Q, "<>Cancelled") | G58: =IF(E58=0, "Never Purchased", "Active Customer") | H58: =IF(E58=0, "Inactive", IF(F58>=50000, "Platinum", IF(F58>=20000, "Gold", IF(F58>=5000, "Silver", "Bronze"))))
A59: 55 | B59: Kiran Saxena | C59: Lucknow | D59: North | E59: =COUNTIFS(Sales_Transactions!C:C, "Kiran Saxena", Sales_Transactions!Q:Q, "<>Cancelled") | F59: =SUMIFS(Sales_Transactions!M:M, Sales_Transactions!C:C, "Kiran Saxena", Sales_Transactions!Q:Q, "<>Cancelled") | G59: =IF(E59=0, "Never Purchased", "Active Customer") | H59: =IF(E59=0, "Inactive", IF(F59>=50000, "Platinum", IF(F59>=20000, "Gold", IF(F59>=5000, "Silver", "Bronze"))))
A60: 56 | B60: Ananya Patel | C60: Jabalpur | D60: Central | E60: =COUNTIFS(Sales_Transactions!C:C, "Ananya Patel", Sales_Transactions!Q:Q, "<>Cancelled") | F60: =SUMIFS(Sales_Transactions!M:M, Sales_Transactions!C:C, "Ananya Patel", Sales_Transactions!Q:Q, "<>Cancelled") | G60: =IF(E60=0, "Never Purchased", "Active Customer") | H60: =IF(E60=0, "Inactive", IF(F60>=50000, "Platinum", IF(F60>=20000, "Gold", IF(F60>=5000, "Silver", "Bronze"))))
A61: 57 | B61: Alok Rao | C61: Jaipur | D61: North | E61: =COUNTIFS(Sales_Transactions!C:C, "Alok Rao", Sales_Transactions!Q:Q, "<>Cancelled") | F61: =SUMIFS(Sales_Transactions!M:M, Sales_Transactions!C:C, "Alok Rao", Sales_Transactions!Q:Q, "<>Cancelled") | G61: =IF(E61=0, "Never Purchased", "Active Customer") | H61: =IF(E61=0, "Inactive", IF(F61>=50000, "Platinum", IF(F61>=20000, "Gold", IF(F61>=5000, "Silver", "Bronze"))))
A62: 58 | B62: Neha Verma | C62: Bhopal | D62: Central | E62: =COUNTIFS(Sales_Transactions!C:C, "Neha Verma", Sales_Transactions!Q:Q, "<>Cancelled") | F62: =SUMIFS(Sales_Transactions!M:M, Sales_Transactions!C:C, "Neha Verma", Sales_Transactions!Q:Q, "<>Cancelled") | G62: =IF(E62=0, "Never Purchased", "Active Customer") | H62: =IF(E62=0, "Inactive", IF(F62>=50000, "Platinum", IF(F62>=20000, "Gold", IF(F62>=5000, "Silver", "Bronze"))))
A63: 59 | B63: Swati Iyer | C63: Indore | D63: Central | E63: =COUNTIFS(Sales_Transactions!C:C, "Swati Iyer", Sales_Transactions!Q:Q, "<>Cancelled") | F63: =SUMIFS(Sales_Transactions!M:M, Sales_Transactions!C:C, "Swati Iyer", Sales_Transactions!Q:Q, "<>Cancelled") | G63: =IF(E63=0, "Never Purchased", "Active Customer") | H63: =IF(E63=0, "Inactive", IF(F63>=50000, "Platinum", IF(F63>=20000, "Gold", IF(F63>=5000, "Silver", "Bronze"))))
A64: 60 | B64: Tarun Verma | C64: Guwahati | D64: East | E64: =COUNTIFS(Sales_Transactions!C:C, "Tarun Verma", Sales_Transactions!Q:Q, "<>Cancelled") | F64: =SUMIFS(Sales_Transactions!M:M, Sales_Transactions!C:C, "Tarun Verma", Sales_Transactions!Q:Q, "<>Cancelled") | G64: =IF(E64=0, "Never Purchased", "Active Customer") | H64: =IF(E64=0, "Inactive", IF(F64>=50000, "Platinum", IF(F64>=20000, "Gold", IF(F64>=5000, "Silver", "Bronze"))))
A65: 61 | B65: Nikhil Deshmukh | C65: Hyderabad | D65: South | E65: =COUNTIFS(Sales_Transactions!C:C, "Nikhil Deshmukh", Sales_Transactions!Q:Q, "<>Cancelled") | F65: =SUMIFS(Sales_Transactions!M:M, Sales_Transactions!C:C, "Nikhil Deshmukh", Sales_Transactions!Q:Q, "<>Cancelled") | G65: =IF(E65=0, "Never Purchased", "Active Customer") | H65: =IF(E65=0, "Inactive", IF(F65>=50000, "Platinum", IF(F65>=20000, "Gold", IF(F65>=5000, "Silver", "Bronze"))))
A66: 62 | B66: Kunal Banerjee | C66: Hyderabad | D66: South | E66: =COUNTIFS(Sales_Transactions!C:C, "Kunal Banerjee", Sales_Transactions!Q:Q, "<>Cancelled") | F66: =SUMIFS(Sales_Transactions!M:M, Sales_Transactions!C:C, "Kunal Banerjee", Sales_Transactions!Q:Q, "<>Cancelled") | G66: =IF(E66=0, "Never Purchased", "Active Customer") | H66: =IF(E66=0, "Inactive", IF(F66>=50000, "Platinum", IF(F66>=20000, "Gold", IF(F66>=5000, "Silver", "Bronze"))))
A67: 63 | B67: Nikhil Verma | C67: Chandigarh | D67: North | E67: =COUNTIFS(Sales_Transactions!C:C, "Nikhil Verma", Sales_Transactions!Q:Q, "<>Cancelled") | F67: =SUMIFS(Sales_Transactions!M:M, Sales_Transactions!C:C, "Nikhil Verma", Sales_Transactions!Q:Q, "<>Cancelled") | G67: =IF(E67=0, "Never Purchased", "Active Customer") | H67: =IF(E67=0, "Inactive", IF(F67>=50000, "Platinum", IF(F67>=20000, "Gold", IF(F67>=5000, "Silver", "Bronze"))))
A68: 64 | B68: Vikram Saxena | C68: Coimbatore | D68: South | E68: =COUNTIFS(Sales_Transactions!C:C, "Vikram Saxena", Sales_Transactions!Q:Q, "<>Cancelled") | F68: =SUMIFS(Sales_Transactions!M:M, Sales_Transactions!C:C, "Vikram Saxena", Sales_Transactions!Q:Q, "<>Cancelled") | G68: =IF(E68=0, "Never Purchased", "Active Customer") | H68: =IF(E68=0, "Inactive", IF(F68>=50000, "Platinum", IF(F68>=20000, "Gold", IF(F68>=5000, "Silver", "Bronze"))))
A69: 65 | B69: Amit Mehta | C69: Noida | D69: North | E69: =COUNTIFS(Sales_Transactions!C:C, "Amit Mehta", Sales_Transactions!Q:Q, "<>Cancelled") | F69: =SUMIFS(Sales_Transactions!M:M, Sales_Transactions!C:C, "Amit Mehta", Sales_Transactions!Q:Q, "<>Cancelled") | G69: =IF(E69=0, "Never Purchased", "Active Customer") | H69: =IF(E69=0, "Inactive", IF(F69>=50000, "Platinum", IF(F69>=20000, "Gold", IF(F69>=5000, "Silver", "Bronze"))))
A70: 66 | B70: Aditya Rao | C70: Guwahati | D70: East | E70: =COUNTIFS(Sales_Transactions!C:C, "Aditya Rao", Sales_Transactions!Q:Q, "<>Cancelled") | F70: =SUMIFS(Sales_Transactions!M:M, Sales_Transactions!C:C, "Aditya Rao", Sales_Transactions!Q:Q, "<>Cancelled") | G70: =IF(E70=0, "Never Purchased", "Active Customer") | H70: =IF(E70=0, "Inactive", IF(F70>=50000, "Platinum", IF(F70>=20000, "Gold", IF(F70>=5000, "Silver", "Bronze"))))
A71: 67 | B71: Tarun Agarwal | C71: Lucknow | D71: North | E71: =COUNTIFS(Sales_Transactions!C:C, "Tarun Agarwal", Sales_Transactions!Q:Q, "<>Cancelled") | F71: =SUMIFS(Sales_Transactions!M:M, Sales_Transactions!C:C, "Tarun Agarwal", Sales_Transactions!Q:Q, "<>Cancelled") | G71: =IF(E71=0, "Never Purchased", "Active Customer") | H71: =IF(E71=0, "Inactive", IF(F71>=50000, "Platinum", IF(F71>=20000, "Gold", IF(F71>=5000, "Silver", "Bronze"))))
A72: 68 | B72: Rajesh Singh | C72: Mumbai | D72: West | E72: =COUNTIFS(Sales_Transactions!C:C, "Rajesh Singh", Sales_Transactions!Q:Q, "<>Cancelled") | F72: =SUMIFS(Sales_Transactions!M:M, Sales_Transactions!C:C, "Rajesh Singh", Sales_Transactions!Q:Q, "<>Cancelled") | G72: =IF(E72=0, "Never Purchased", "Active Customer") | H72: =IF(E72=0, "Inactive", IF(F72>=50000, "Platinum", IF(F72>=20000, "Gold", IF(F72>=5000, "Silver", "Bronze"))))
A73: 69 | B73: Harsh Singh | C73: Ahmedabad | D73: West | E73: =COUNTIFS(Sales_Transactions!C:C, "Harsh Singh", Sales_Transactions!Q:Q, "<>Cancelled") | F73: =SUMIFS(Sales_Transactions!M:M, Sales_Transactions!C:C, "Harsh Singh", Sales_Transactions!Q:Q, "<>Cancelled") | G73: =IF(E73=0, "Never Purchased", "Active Customer") | H73: =IF(E73=0, "Inactive", IF(F73>=50000, "Platinum", IF(F73>=20000, "Gold", IF(F73>=5000, "Silver", "Bronze"))))
A74: 70 | B74: Deepika Nair | C74: Nagpur | D74: West | E74: =COUNTIFS(Sales_Transactions!C:C, "Deepika Nair", Sales_Transactions!Q:Q, "<>Cancelled") | F74: =SUMIFS(Sales_Transactions!M:M, Sales_Transactions!C:C, "Deepika Nair", Sales_Transactions!Q:Q, "<>Cancelled") | G74: =IF(E74=0, "Never Purchased", "Active Customer") | H74: =IF(E74=0, "Inactive", IF(F74>=50000, "Platinum", IF(F74>=20000, "Gold", IF(F74>=5000, "Silver", "Bronze"))))
A75: 71 | B75: Kunal Patel | C75: Lucknow | D75: North | E75: =COUNTIFS(Sales_Transactions!C:C, "Kunal Patel", Sales_Transactions!Q:Q, "<>Cancelled") | F75: =SUMIFS(Sales_Transactions!M:M, Sales_Transactions!C:C, "Kunal Patel", Sales_Transactions!Q:Q, "<>Cancelled") | G75: =IF(E75=0, "Never Purchased", "Active Customer") | H75: =IF(E75=0, "Inactive", IF(F75>=50000, "Platinum", IF(F75>=20000, "Gold", IF(F75>=5000, "Silver", "Bronze"))))
A76: 72 | B76: Meera Patel | C76: Gurgaon | D76: North | E76: =COUNTIFS(Sales_Transactions!C:C, "Meera Patel", Sales_Transactions!Q:Q, "<>Cancelled") | F76: =SUMIFS(Sales_Transactions!M:M, Sales_Transactions!C:C, "Meera Patel", Sales_Transactions!Q:Q, "<>Cancelled") | G76: =IF(E76=0, "Never Purchased", "Active Customer") | H76: =IF(E76=0, "Inactive", IF(F76>=50000, "Platinum", IF(F76>=20000, "Gold", IF(F76>=5000, "Silver", "Bronze"))))
A77: 73 | B77: Kunal Rao | C77: Guwahati | D77: East | E77: =COUNTIFS(Sales_Transactions!C:C, "Kunal Rao", Sales_Transactions!Q:Q, "<>Cancelled") | F77: =SUMIFS(Sales_Transactions!M:M, Sales_Transactions!C:C, "Kunal Rao", Sales_Transactions!Q:Q, "<>Cancelled") | G77: =IF(E77=0, "Never Purchased", "Active Customer") | H77: =IF(E77=0, "Inactive", IF(F77>=50000, "Platinum", IF(F77>=20000, "Gold", IF(F77>=5000, "Silver", "Bronze"))))
A78: 74 | B78: Harsh Sharma | C78: Delhi | D78: North | E78: =COUNTIFS(Sales_Transactions!C:C, "Harsh Sharma", Sales_Transactions!Q:Q, "<>Cancelled") | F78: =SUMIFS(Sales_Transactions!M:M, Sales_Transactions!C:C, "Harsh Sharma", Sales_Transactions!Q:Q, "<>Cancelled") | G78: =IF(E78=0, "Never Purchased", "Active Customer") | H78: =IF(E78=0, "Inactive", IF(F78>=50000, "Platinum", IF(F78>=20000, "Gold", IF(F78>=5000, "Silver", "Bronze"))))
A79: 75 | B79: Nandini Patel | C79: Nagpur | D79: West | E79: =COUNTIFS(Sales_Transactions!C:C, "Nandini Patel", Sales_Transactions!Q:Q, "<>Cancelled") | F79: =SUMIFS(Sales_Transactions!M:M, Sales_Transactions!C:C, "Nandini Patel", Sales_Transactions!Q:Q, "<>Cancelled") | G79: =IF(E79=0, "Never Purchased", "Active Customer") | H79: =IF(E79=0, "Inactive", IF(F79>=50000, "Platinum", IF(F79>=20000, "Gold", IF(F79>=5000, "Silver", "Bronze"))))
A80: 76 | B80: Anjali Singh | C80: Gurgaon | D80: North | E80: =COUNTIFS(Sales_Transactions!C:C, "Anjali Singh", Sales_Transactions!Q:Q, "<>Cancelled") | F80: =SUMIFS(Sales_Transactions!M:M, Sales_Transactions!C:C, "Anjali Singh", Sales_Transactions!Q:Q, "<>Cancelled") | G80: =IF(E80=0, "Never Purchased", "Active Customer") | H80: =IF(E80=0, "Inactive", IF(F80>=50000, "Platinum", IF(F80>=20000, "Gold", IF(F80>=5000, "Silver", "Bronze"))))
A81: 77 | B81: Rohit Mehta | C81: Chennai | D81: South | E81: =COUNTIFS(Sales_Transactions!C:C, "Rohit Mehta", Sales_Transactions!Q:Q, "<>Cancelled") | F81: =SUMIFS(Sales_Transactions!M:M, Sales_Transactions!C:C, "Rohit Mehta", Sales_Transactions!Q:Q, "<>Cancelled") | G81: =IF(E81=0, "Never Purchased", "Active Customer") | H81: =IF(E81=0, "Inactive", IF(F81>=50000, "Platinum", IF(F81>=20000, "Gold", IF(F81>=5000, "Silver", "Bronze"))))
A82: 78 | B82: Sunil Saxena | C82: Guwahati | D82: East | E82: =COUNTIFS(Sales_Transactions!C:C, "Sunil Saxena", Sales_Transactions!Q:Q, "<>Cancelled") | F82: =SUMIFS(Sales_Transactions!M:M, Sales_Transactions!C:C, "Sunil Saxena", Sales_Transactions!Q:Q, "<>Cancelled") | G82: =IF(E82=0, "Never Purchased", "Active Customer") | H82: =IF(E82=0, "Inactive", IF(F82>=50000, "Platinum", IF(F82>=20000, "Gold", IF(F82>=5000, "Silver", "Bronze"))))
A83: 79 | B83: Shreya Rao | C83: Kochi | D83: South | E83: =COUNTIFS(Sales_Transactions!C:C, "Shreya Rao", Sales_Transactions!Q:Q, "<>Cancelled") | F83: =SUMIFS(Sales_Transactions!M:M, Sales_Transactions!C:C, "Shreya Rao", Sales_Transactions!Q:Q, "<>Cancelled") | G83: =IF(E83=0, "Never Purchased", "Active Customer") | H83: =IF(E83=0, "Inactive", IF(F83>=50000, "Platinum", IF(F83>=20000, "Gold", IF(F83>=5000, "Silver", "Bronze"))))
A84: 80 | B84: Neha Reddy | C84: Bhubaneswar | D84: East | E84: =COUNTIFS(Sales_Transactions!C:C, "Neha Reddy", Sales_Transactions!Q:Q, "<>Cancelled") | F84: =SUMIFS(Sales_Transactions!M:M, Sales_Transactions!C:C, "Neha Reddy", Sales_Transactions!Q:Q, "<>Cancelled") | G84: =IF(E84=0, "Never Purchased", "Active Customer") | H84: =IF(E84=0, "Inactive", IF(F84>=50000, "Platinum", IF(F84>=20000, "Gold", IF(F84>=5000, "Silver", "Bronze"))))
A85: 81 | B85: Suresh Iyer | C85: Kolkata | D85: East | E85: =COUNTIFS(Sales_Transactions!C:C, "Suresh Iyer", Sales_Transactions!Q:Q, "<>Cancelled") | F85: =SUMIFS(Sales_Transactions!M:M, Sales_Transactions!C:C, "Suresh Iyer", Sales_Transactions!Q:Q, "<>Cancelled") | G85: =IF(E85=0, "Never Purchased", "Active Customer") | H85: =IF(E85=0, "Inactive", IF(F85>=50000, "Platinum", IF(F85>=20000, "Gold", IF(F85>=5000, "Silver", "Bronze"))))
A86: 82 | B86: Manoj Nair | C86: Patna | D86: East | E86: =COUNTIFS(Sales_Transactions!C:C, "Manoj Nair", Sales_Transactions!Q:Q, "<>Cancelled") | F86: =SUMIFS(Sales_Transactions!M:M, Sales_Transactions!C:C, "Manoj Nair", Sales_Transactions!Q:Q, "<>Cancelled") | G86: =IF(E86=0, "Never Purchased", "Active Customer") | H86: =IF(E86=0, "Inactive", IF(F86>=50000, "Platinum", IF(F86>=20000, "Gold", IF(F86>=5000, "Silver", "Bronze"))))
A87: 83 | B87: Manoj Gupta | C87: Lucknow | D87: North | E87: =COUNTIFS(Sales_Transactions!C:C, "Manoj Gupta", Sales_Transactions!Q:Q, "<>Cancelled") | F87: =SUMIFS(Sales_Transactions!M:M, Sales_Transactions!C:C, "Manoj Gupta", Sales_Transactions!Q:Q, "<>Cancelled") | G87: =IF(E87=0, "Never Purchased", "Active Customer") | H87: =IF(E87=0, "Inactive", IF(F87>=50000, "Platinum", IF(F87>=20000, "Gold", IF(F87>=5000, "Silver", "Bronze"))))
A88: 84 | B88: Swati Reddy | C88: Mumbai | D88: West | E88: =COUNTIFS(Sales_Transactions!C:C, "Swati Reddy", Sales_Transactions!Q:Q, "<>Cancelled") | F88: =SUMIFS(Sales_Transactions!M:M, Sales_Transactions!C:C, "Swati Reddy", Sales_Transactions!Q:Q, "<>Cancelled") | G88: =IF(E88=0, "Never Purchased", "Active Customer") | H88: =IF(E88=0, "Inactive", IF(F88>=50000, "Platinum", IF(F88>=20000, "Gold", IF(F88>=5000, "Silver", "Bronze"))))
A89: 85 | B89: Sunil Agarwal | C89: Guwahati | D89: East | E89: =COUNTIFS(Sales_Transactions!C:C, "Sunil Agarwal", Sales_Transactions!Q:Q, "<>Cancelled") | F89: =SUMIFS(Sales_Transactions!M:M, Sales_Transactions!C:C, "Sunil Agarwal", Sales_Transactions!Q:Q, "<>Cancelled") | G89: =IF(E89=0, "Never Purchased", "Active Customer") | H89: =IF(E89=0, "Inactive", IF(F89>=50000, "Platinum", IF(F89>=20000, "Gold", IF(F89>=5000, "Silver", "Bronze"))))
A90: 86 | B90: Priya Iyer | C90: Pune | D90: West | E90: =COUNTIFS(Sales_Transactions!C:C, "Priya Iyer", Sales_Transactions!Q:Q, "<>Cancelled") | F90: =SUMIFS(Sales_Transactions!M:M, Sales_Transactions!C:C, "Priya Iyer", Sales_Transactions!Q:Q, "<>Cancelled") | G90: =IF(E90=0, "Never Purchased", "Active Customer") | H90: =IF(E90=0, "Inactive", IF(F90>=50000, "Platinum", IF(F90>=20000, "Gold", IF(F90>=5000, "Silver", "Bronze"))))
A91: 87 | B91: Rohit Iyer | C91: Jabalpur | D91: Central | E91: =COUNTIFS(Sales_Transactions!C:C, "Rohit Iyer", Sales_Transactions!Q:Q, "<>Cancelled") | F91: =SUMIFS(Sales_Transactions!M:M, Sales_Transactions!C:C, "Rohit Iyer", Sales_Transactions!Q:Q, "<>Cancelled") | G91: =IF(E91=0, "Never Purchased", "Active Customer") | H91: =IF(E91=0, "Inactive", IF(F91>=50000, "Platinum", IF(F91>=20000, "Gold", IF(F91>=5000, "Silver", "Bronze"))))
A92: 88 | B92: Nikhil Joshi | C92: Gwalior | D92: Central | E92: =COUNTIFS(Sales_Transactions!C:C, "Nikhil Joshi", Sales_Transactions!Q:Q, "<>Cancelled") | F92: =SUMIFS(Sales_Transactions!M:M, Sales_Transactions!C:C, "Nikhil Joshi", Sales_Transactions!Q:Q, "<>Cancelled") | G92: =IF(E92=0, "Never Purchased", "Active Customer") | H92: =IF(E92=0, "Inactive", IF(F92>=50000, "Platinum", IF(F92>=20000, "Gold", IF(F92>=5000, "Silver", "Bronze"))))
A93: 89 | B93: Gaurav Malhotra | C93: Hyderabad | D93: South | E93: =COUNTIFS(Sales_Transactions!C:C, "Gaurav Malhotra", Sales_Transactions!Q:Q, "<>Cancelled") | F93: =SUMIFS(Sales_Transactions!M:M, Sales_Transactions!C:C, "Gaurav Malhotra", Sales_Transactions!Q:Q, "<>Cancelled") | G93: =IF(E93=0, "Never Purchased", "Active Customer") | H93: =IF(E93=0, "Inactive", IF(F93>=50000, "Platinum", IF(F93>=20000, "Gold", IF(F93>=5000, "Silver", "Bronze"))))
A94: 90 | B94: Anjali Sharma | C94: Gwalior | D94: Central | E94: =COUNTIFS(Sales_Transactions!C:C, "Anjali Sharma", Sales_Transactions!Q:Q, "<>Cancelled") | F94: =SUMIFS(Sales_Transactions!M:M, Sales_Transactions!C:C, "Anjali Sharma", Sales_Transactions!Q:Q, "<>Cancelled") | G94: =IF(E94=0, "Never Purchased", "Active Customer") | H94: =IF(E94=0, "Inactive", IF(F94>=50000, "Platinum", IF(F94>=20000, "Gold", IF(F94>=5000, "Silver", "Bronze"))))
A95: 91 | B95: Tanvi Joshi | C95: Lucknow | D95: North | E95: =COUNTIFS(Sales_Transactions!C:C, "Tanvi Joshi", Sales_Transactions!Q:Q, "<>Cancelled") | F95: =SUMIFS(Sales_Transactions!M:M, Sales_Transactions!C:C, "Tanvi Joshi", Sales_Transactions!Q:Q, "<>Cancelled") | G95: =IF(E95=0, "Never Purchased", "Active Customer") | H95: =IF(E95=0, "Inactive", IF(F95>=50000, "Platinum", IF(F95>=20000, "Gold", IF(F95>=5000, "Silver", "Bronze"))))
A96: 92 | B96: Tarun Reddy | C96: Lucknow | D96: North | E96: =COUNTIFS(Sales_Transactions!C:C, "Tarun Reddy", Sales_Transactions!Q:Q, "<>Cancelled") | F96: =SUMIFS(Sales_Transactions!M:M, Sales_Transactions!C:C, "Tarun Reddy", Sales_Transactions!Q:Q, "<>Cancelled") | G96: =IF(E96=0, "Never Purchased", "Active Customer") | H96: =IF(E96=0, "Inactive", IF(F96>=50000, "Platinum", IF(F96>=20000, "Gold", IF(F96>=5000, "Silver", "Bronze"))))
A97: 93 | B97: Rhea Choudhury | C97: Patna | D97: East | E97: =COUNTIFS(Sales_Transactions!C:C, "Rhea Choudhury", Sales_Transactions!Q:Q, "<>Cancelled") | F97: =SUMIFS(Sales_Transactions!M:M, Sales_Transactions!C:C, "Rhea Choudhury", Sales_Transactions!Q:Q, "<>Cancelled") | G97: =IF(E97=0, "Never Purchased", "Active Customer") | H97: =IF(E97=0, "Inactive", IF(F97>=50000, "Platinum", IF(F97>=20000, "Gold", IF(F97>=5000, "Silver", "Bronze"))))
A98: 94 | B98: Aditya Saxena | C98: Chennai | D98: South | E98: =COUNTIFS(Sales_Transactions!C:C, "Aditya Saxena", Sales_Transactions!Q:Q, "<>Cancelled") | F98: =SUMIFS(Sales_Transactions!M:M, Sales_Transactions!C:C, "Aditya Saxena", Sales_Transactions!Q:Q, "<>Cancelled") | G98: =IF(E98=0, "Never Purchased", "Active Customer") | H98: =IF(E98=0, "Inactive", IF(F98>=50000, "Platinum", IF(F98>=20000, "Gold", IF(F98>=5000, "Silver", "Bronze"))))
A99: 95 | B99: Gaurav Rao | C99: Gwalior | D99: Central | E99: =COUNTIFS(Sales_Transactions!C:C, "Gaurav Rao", Sales_Transactions!Q:Q, "<>Cancelled") | F99: =SUMIFS(Sales_Transactions!M:M, Sales_Transactions!C:C, "Gaurav Rao", Sales_Transactions!Q:Q, "<>Cancelled") | G99: =IF(E99=0, "Never Purchased", "Active Customer") | H99: =IF(E99=0, "Inactive", IF(F99>=50000, "Platinum", IF(F99>=20000, "Gold", IF(F99>=5000, "Silver", "Bronze"))))
A100: 96 | B100: Swati Saxena | C100: Gurgaon | D100: North | E100: =COUNTIFS(Sales_Transactions!C:C, "Swati Saxena", Sales_Transactions!Q:Q, "<>Cancelled") | F100: =SUMIFS(Sales_Transactions!M:M, Sales_Transactions!C:C, "Swati Saxena", Sales_Transactions!Q:Q, "<>Cancelled") | G100: =IF(E100=0, "Never Purchased", "Active Customer") | H100: =IF(E100=0, "Inactive", IF(F100>=50000, "Platinum", IF(F100>=20000, "Gold", IF(F100>=5000, "Silver", "Bronze"))))
A101: 97 | B101: Divya Joshi | C101: Gwalior | D101: Central | E101: =COUNTIFS(Sales_Transactions!C:C, "Divya Joshi", Sales_Transactions!Q:Q, "<>Cancelled") | F101: =SUMIFS(Sales_Transactions!M:M, Sales_Transactions!C:C, "Divya Joshi", Sales_Transactions!Q:Q, "<>Cancelled") | G101: =IF(E101=0, "Never Purchased", "Active Customer") | H101: =IF(E101=0, "Inactive", IF(F101>=50000, "Platinum", IF(F101>=20000, "Gold", IF(F101>=5000, "Silver", "Bronze"))))
A102: 98 | B102: Simran Bhat | C102: Bhubaneswar | D102: East | E102: =COUNTIFS(Sales_Transactions!C:C, "Simran Bhat", Sales_Transactions!Q:Q, "<>Cancelled") | F102: =SUMIFS(Sales_Transactions!M:M, Sales_Transactions!C:C, "Simran Bhat", Sales_Transactions!Q:Q, "<>Cancelled") | G102: =IF(E102=0, "Never Purchased", "Active Customer") | H102: =IF(E102=0, "Inactive", IF(F102>=50000, "Platinum", IF(F102>=20000, "Gold", IF(F102>=5000, "Silver", "Bronze"))))
...
